{"schema_version":1,"updated_at":"2026-04-20T15:41:28.103772+00:00","total":60,"articles":[{"id":"http://blog.livedoor.jp/nanjstu/archives/63141704.html","title":"ガンダムSEED DESTINY 連合 VS. Z.A.F.T.Ⅱとかいう20年前のゲームｗｗｗｗｗｗ","url":"http://blog.livedoor.jp/nanjstu/archives/63141704.html","published":"2026-04-14T16:04:44+09:00","thumbnail":"https://wsrv.nl/?url=https%3A%2F%2Flivedoor.blogimg.jp%2Fnanjstu%2Fimgs%2F3%2F2%2F320c9166.jpg&w=200&h=200&output=webp&q=80","site_id":"blog_livedoor_jp_nanjstu","site_name":"なんじぇいスタジアム＠なんJまとめ","hatena_bookmarks":0,"category":"anige","rank":6},{"id":"http://morikinoko.com/archives/52210226.html","title":"輿水幸子「安価でPさんに料理を作ります」","url":"http://morikinoko.com/archives/52210226.html","published":"2026-04-20T21:05:08+09:00","thumbnail":null,"site_id":"morikinoko_com","site_name":"SS 森きのこ！","category":"anige","hatena_bookmarks":0,"rank":9},{"id":"https://uma-log.net/?p=4410877","title":"【ウマ娘】うわ、こいつチョコまで全部食ってやがる！？","url":"https://uma-log.net/4410877/","published":"Mon, 20 Apr 2026 12:01:00 +0000","thumbnail":"https://wsrv.nl/?url=https%3A%2F%2Fuma-log.net%2Fwp-content%2Fuploads%2F2026%2F04%2Ff727fb15kI-405x720.png&w=200&h=200&output=webp&q=80","site_id":"uma_log_net","site_name":"うまろぐ","category":"anige","hatena_bookmarks":0,"rank":10},{"id":"https://switchsoku.com/?p=122024","title":"『ドラクエ』やっぱり順番ずつやっていった方がいいのか？","url":"https://switchsoku.com/soft/dragonquest/122024","published":"Mon, 20 Apr 2026 12:00:53 +0000","thumbnail":null,"site_id":"switchsoku_com","site_name":"SWITCH速報","category":"anige","hatena_bookmarks":0,"rank":11},{"id":"https://chomangasokuho.blog.jp/archives/38286108.html","title":"銀魂作者の新作漫画、クソつまらないWWWWWWWWWW","url":"https://chomangasokuho.blog.jp/archives/38286108.html","published":"2026-04-20T20:30:52+09:00","thumbnail":"https://wsrv.nl/?url=https%3A%2F%2Flivedoor.blogimg.jp%2Fheroakasoku%2Fimgs%2Fe%2F0%2Fe0cb8c7f.jpg&w=200&h=200&output=webp&q=80","site_id":"chomangasokuho_blog_jp","site_name":"超・マンガ速報","category":"anige","hatena_bookmarks":0,"rank":12},{"id":"https://jumpmatome2ch.biz/?p=401325","title":"今週の「ロクのおかしな家」感想、ばあちゃんの見舞いと居候の許可を取りに行くヨハンの運命は！？【3話】","url":"https://jumpmatome2ch.biz/archives/401325","published":"Mon, 20 Apr 2026 11:24:05 +0000","thumbnail":"https://wsrv.nl/?url=https%3A%2F%2Fjumpmatome2ch.biz%2Fwp-content%2Fuploads%2F2026%2F04%2Froku.jpg&w=200&h=200&output=webp&q=80","site_id":"jumpmatome2ch_biz","site_name":"ジャンプまとめ速報","category":"anige","hatena_bookmarks":0,"rank":13},{"id":"https://www.mutyun.com/?p=263667","title":"任天堂、最近子供向けゲームに逃げてない？","url":"https://www.mutyun.com/archives/263667.html","published":"Mon, 20 Apr 2026 11:02:46 +0000","thumbnail":"https://wsrv.nl/?url=https%3A%2F%2Fimg.mutyun.com%2Fkyoko%2F2026%2F03%2F09%2FftpZgH.jpg&w=200&h=200&output=webp&q=80","site_id":"www_mutyun_com","site_name":"mutyunのゲーム+αブログ","category":"anige","hatena_bookmarks":0,"rank":15},{"id":"https://lovelivematocha.com/blog-entry-66951.html","title":"【画像】やっぱりさやかちゃんってさ・・・【ラブライブ！蓮ノ空】","url":"https://lovelivematocha.com/blog-entry-66951.html","published":"2026-04-20T19:00:00+09:00","thumbnail":"https://wsrv.nl/?url=https%3A%2F%2Fblog-imgs-183.fc2.com%2Fl%2Fo%2Fv%2Flovelivematocha%2Ff4ZkbHAs.jpg&w=200&h=200&output=webp&q=80","site_id":"lovelivematocha_com","site_name":"ラブライブ！まとめちゃんねる！！","category":"anige","hatena_bookmarks":0,"rank":19},{"id":"https://j-seiji.blog.jp/archives/29812995.html","title":"【自民党大会】自衛隊陸幕長「指示されたら制服を着用できる規則だが、勝手に着ても違反ではない」記者「おかしくね？じゃあその規則は何のためにあるのか？」","url":"https://j-seiji.blog.jp/archives/29812995.html","published":"2026-04-20T16:34:00+09:00","thumbnail":"https://wsrv.nl/?url=https%3A%2F%2Flivedoor.blogimg.jp%2Fmaaikkana%2Fimgs%2F9%2F9%2F992586b9-s.png&w=200&h=200&output=webp&q=80","site_id":"j_seiji_blog_jp","site_name":"なんJ政治ネタまとめ","category":"news","hatena_bookmarks":0,"rank":1},{"id":"http://blog.livedoor.jp/itsoku/archives/63154569.html","title":"【悲報】トランプ大統領、本性を現す「もういい人はやめだ！」","url":"http://blog.livedoor.jp/itsoku/archives/63154569.html","published":"2026-04-20T07:47:33+09:00","thumbnail":"https://wsrv.nl/?url=https%3A%2F%2Flivedoor.blogimg.jp%2Fitsoku%2Fimgs%2Fe%2Ff%2Fef428b59-s.png&w=200&h=200&output=webp&q=80","site_id":"blog_livedoor_jp_itsoku","site_name":"IT速報","category":"news","hatena_bookmarks":0,"rank":2},{"id":"http://blog.livedoor.jp/corez18c24-mili777/archives/59802428.html","title":"日本が外交青書で中国を「格下げ」、日中関係に改善の兆しなし…香港メディア！","url":"http://blog.livedoor.jp/corez18c24-mili777/archives/59802428.html","published":"2026-04-20T13:35:02+09:00","thumbnail":"https://wsrv.nl/?url=https%3A%2F%2Flivedoor.blogimg.jp%2Fcorez18c24-mili777%2Fimgs%2F2%2Fc%2F2c2ac119.jpg&w=200&h=200&output=webp&q=80","site_id":"blog_livedoor_jp_corez18c24_mili777","site_name":"軍事・ミリタリー速報☆彡","category":"news","hatena_bookmarks":0,"rank":3},{"id":"http://blog.livedoor.jp/bluejay01-review/archives/63153512.html","title":"【ルーター】家電量販店で見るとatermの売り場大分狭くなったよね","url":"http://blog.livedoor.jp/bluejay01-review/archives/63153512.html","published":"2026-04-20T06:01:58+09:00","thumbnail":"https://wsrv.nl/?url=https%3A%2F%2Flivedoor.blogimg.jp%2Fbluejay01-review%2Fimgs%2F5%2Fd%2F5d016883-s.jpg&w=200&h=200&output=webp&q=80","site_id":"blog_livedoor_jp_bluejay01_review","site_name":"PCパーツまとめ","category":"news","hatena_bookmarks":0,"rank":4},{"id":"http://blog.livedoor.jp/corez18c24-mili777/archives/59800520.html","title":"中東戦争の隙突き、中国が南シナ海に「浮遊式障害物」設置！","url":"http://blog.livedoor.jp/corez18c24-mili777/archives/59800520.html","published":"2026-04-20T02:31:05+09:00","thumbnail":"https://wsrv.nl/?url=https%3A%2F%2Flivedoor.blogimg.jp%2Fcorez18c24-mili777%2Fimgs%2Fd%2Fd%2Fdd08824b.jpg&w=200&h=200&output=webp&q=80","site_id":"blog_livedoor_jp_corez18c24_mili777","site_name":"軍事・ミリタリー速報☆彡","category":"news","hatena_bookmarks":0,"rank":5},{"id":"https://toushichannel.net/archives/46025983.html","title":"【悲報】ラーメン屋「現金会計のみです」←これ","url":"https://toushichannel.net/archives/46025983.html","published":"2026-04-20T08:00:04+09:00","thumbnail":null,"site_id":"toushichannel_net","site_name":"投資ちゃんねる","category":"news","hatena_bookmarks":0,"rank":6},{"id":"https://crx7601.com/archives/63153379.html","title":"【速報】ロイター通信「中国、日本とは違い不動産バブルを乗り越える！」→AI「経営破綻した中国恒大集団など大手デベロッパーも債務再編の途上、隠れ債務2,000兆円規模（IMF推計」","url":"https://crx7601.com/archives/63153379.html","published":"2026-04-20T05:06:16+09:00","thumbnail":"https://wsrv.nl/?url=https%3A%2F%2Flivedoor.blogimg.jp%2Fcrx7601%2Fimgs%2F7%2F0%2F7066f01c.jpg&w=200&h=200&output=webp&q=80","site_id":"crx7601_com","site_name":"おーるじゃんる","category":"news","rank":7,"hatena_bookmarks":0},{"id":"https://incident-wo.com/?p=122545","title":"国民民主・伊藤孝恵氏が激怒　辺野古事故の校長発言報道に絶句「なんて非道な言葉を使う教育者」 『学校はある意味でリスタートします』","url":"https://incident-wo.com/post-122545/","published":"Mon, 20 Apr 2026 09:29:00 +0000","thumbnail":null,"site_id":"incident_wo_com","site_name":"日本第一！ニュース録","category":"news","hatena_bookmarks":0,"rank":8},{"id":"https://thainokoe.com/?p=10023030","title":"日本人「これが名古屋のコーヒーゼリーじゃよ」→カロリーの化け物ｗドリルにしか見えないｗ【タイ人の反応】","url":"https://thainokoe.com/this-is-nagoyas-coffee-jelly/","published":"Mon, 20 Apr 2026 03:15:54 +0000","thumbnail":"https://wsrv.nl/?url=https%3A%2F%2Fthainokoe.com%2Fwp-content%2Fuploads%2F2025%2F12%2F251229_70f2qu7coxs0.jpg&w=200&h=200&output=webp&q=80","site_id":"thainokoe_com","site_name":"タイの反応 タイコエ","category":"news","hatena_bookmarks":0,"rank":9},{"id":"https://no-one-no.net/archives/48364476.html","title":"【海外の反応】吸血鬼の心臓に杭を打ち込んだら想定外の血の噴水が爆発する映画の名シーン　「もう死んでるから大丈夫」「新聞敷いときゃよかった」","url":"https://no-one-no.net/archives/48364476.html","published":"2026-04-20T11:10:46+09:00","thumbnail":"https://wsrv.nl/?url=https%3A%2F%2Flivedoor.blogimg.jp%2Ftanukiparapara%2Fimgs%2F2%2Ff%2F2f9a16fd.jpg&w=200&h=200&output=webp&q=80","site_id":"no_one_no_net","site_name":"QQQ(海外の反応)","category":"news","hatena_bookmarks":0,"rank":10},{"id":"https://foreignnews.biz/?p=212595","title":"オランダ「多文化共生社会実現の為に！」学生125人と難民125人を実験的に共同生活させた結果⇒難民による強姦・暴行事件が多発[海外の反応]","url":"https://foreignnews.biz/archives/post-212595.html","published":"Mon, 20 Apr 2026 04:39:26 +0000","thumbnail":"https://wsrv.nl/?url=https%3A%2F%2Fblog.with2.net%2Fimg%2Fbanner%2Fm02%2Fbr_banner_brcat.gif&w=200&h=200&output=webp&q=80","site_id":"foreignnews_biz_archives_cat_382414_xml","site_name":"海外の反応 | 海外報道翻訳所","category":"news","hatena_bookmarks":0,"rank":11},{"id":"https://crx7601.com/archives/63154772.html","title":"【速報】中道改革連合の支持率爆増、支持率が前回比150%を記録！！","url":"https://crx7601.com/archives/63154772.html","published":"2026-04-20T15:06:36+09:00","thumbnail":"https://wsrv.nl/?url=https%3A%2F%2Flivedoor.blogimg.jp%2Fcrx7601%2Fimgs%2F7%2Ff%2F7f599094.png&w=200&h=200&output=webp&q=80","site_id":"crx7601_com","site_name":"おーるじゃんる","category":"news","hatena_bookmarks":0,"rank":12},{"id":"http://blog.livedoor.jp/yu_ps13/archives/51687147.html","title":"世界でEV販売急増、イラン情勢でガソリン高騰・原油供給への不安広がり…HVの日本車に逆風","url":"http://blog.livedoor.jp/yu_ps13/archives/51687147.html","published":"2026-04-20T11:50:36+09:00","thumbnail":null,"site_id":"blog_livedoor_jp_yu_ps13","site_name":"ゆめ痛 -NEWS ALERT-","category":"news","hatena_bookmarks":0,"rank":13},{"id":"https://you1news.com/?p=193770","title":"京都男児遺棄事件に言及したサンモニ出演者、「究極のおまいう案件すぎる」と視聴者を驚愕させる内容を……","url":"https://you1news.com/archives/193770.html","published":"Sun, 19 Apr 2026 18:06:34 +0000","thumbnail":null,"site_id":"you1news_com","site_name":"U-1 NEWS","category":"news","hatena_bookmarks":0,"rank":15},{"id":"http://www.watch2chan.com/archives/20260419205424.html","title":"【悲報】東京科学大学(元東工大)の女子枠比率、限界突破ｗｗｗｗｗｗｗｗｗ","url":"http://www.watch2chan.com/archives/20260419205424.html","published":"2026-04-19T18:03:44Z","thumbnail":null,"site_id":"www_watch2chan_com","site_name":"watch＠２ちゃんねる","category":"news","hatena_bookmarks":0,"rank":17},{"id":"https://beikokukabu-etf-matome.com/archives/%e3%82%aa%e3%83%ab%e3%82%ab%e3%83%b3%e5%b9%b4%e5%88%a95%e3%81%a7%e6%96%b0nisa%e6%9e%a0%e3%82%92%e6%ba%80%e9%a1%8d%e5%9f%8b%e3%82%81%e3%82%8b%e3%81%a818%e5%b9%b4%e5%be%8c%e3%81%ab%e3%81%af%e6%af%8e.html","title":"オルカン(年利5%)で新NISA枠を満額埋めると18年後には毎月20万円引き出しても資産が減らなくなる","url":"https://beikokukabu-etf-matome.com/archives/%e3%82%aa%e3%83%ab%e3%82%ab%e3%83%b3%e5%b9%b4%e5%88%a95%e3%81%a7%e6%96%b0nisa%e6%9e%a0%e3%82%92%e6%ba%80%e9%a1%8d%e5%9f%8b%e3%82%81%e3%82%8b%e3%81%a818%e5%b9%b4%e5%be%8c%e3%81%ab%e3%81%af%e6%af%8e.html","published":"2026-04-19T21:00:22Z","thumbnail":"https://wsrv.nl/?url=https%3A%2F%2Fbeikokukabu-etf-matome.com%2Fwp-content%2Fuploads%2F2024%2F06%2Fimage_123650291-3-150x150.jpg&w=200&h=200&output=webp&q=80","site_id":"beikokukabu_etf_matome_com","site_name":"米国株ETFまとめ速報","category":"news","hatena_bookmarks":0,"rank":18},{"id":"https://marutoo.com/?p=12449","title":"海外「速報！村上宗孝3試合連発の季8号ホームランを放つ！」","url":"https://marutoo.com/murakami-eighth-home-run/","published":"Sun, 19 Apr 2026 22:57:10 +0000","thumbnail":"https://wsrv.nl/?url=https%3A%2F%2Fmarutoo.com%2Fwp-content%2Fuploads%2F2024%2F08%2F%E3%82%B9%E3%82%AF%E3%83%AA%E3%83%BC%E3%83%B3%E3%82%B7%E3%83%A7%E3%83%83%E3%83%88-2024-08-02-044920.jpg&w=200&h=200&output=webp&q=80","site_id":"marutoo_com","site_name":"まるっと翻訳","category":"news","hatena_bookmarks":0,"rank":19},{"id":"https://you1news.com/?p=193804","title":"「転覆事故の際に救難信号を出さずに隠蔽工作しようとした？」との疑惑が浮上している模様、生徒たちの証言によって異常な行動が明らかになり……","url":"https://you1news.com/archives/193804.html","published":"Mon, 20 Apr 2026 04:09:16 +0000","thumbnail":null,"site_id":"you1news_com","site_name":"U-1 NEWS","category":"news","hatena_bookmarks":0,"rank":20},{"id":"https://1000mg.jp/?p=247370","title":"【動画】なぞ運転のトラックと衝突して愛車を壊されたスバル360乗りのドラレコ。","url":"https://1000mg.jp/247370/","published":"Mon, 20 Apr 2026 03:00:15 +0000","thumbnail":"https://wsrv.nl/?url=https%3A%2F%2F1000mg.jp%2Fwp-content%2Fuploads%2F2026%2F04%2Fvideoframe_6324.jpg&w=200&h=200&output=webp&q=80","site_id":"1000mg_jp","site_name":"1000mg","category":"neta","hatena_bookmarks":1,"rank":2},{"id":"https://netizen-voice.blog.jp/archives/47013988.html","title":"【速報】めるる、意外とデカい","url":"https://netizen-voice.blog.jp/archives/47013988.html","published":"2026-04-20T14:00:59+09:00","thumbnail":"https://wsrv.nl/?url=https%3A%2F%2Flivedoor.blogimg.jp%2Fnetizen_reaction%2Fimgs%2Ff%2Fa%2Ffab89a8f-s.jpg&w=200&h=200&output=webp&q=80","site_id":"netizen_voice_blog_jp","site_name":"ネラーボイス","category":"neta","hatena_bookmarks":0,"rank":3},{"id":"https://pokemon-goh.doorblog.jp/archives/46031783.html","title":"【衝撃】最近の軽自動車さん、うっかり普通車よりカッコよくなってしまうｗｗｗｗｗ(※画像あり)","url":"https://pokemon-goh.doorblog.jp/archives/46031783.html","published":"2026-04-20T16:18:09+09:00","thumbnail":"https://wsrv.nl/?url=https%3A%2F%2Flivedoor.blogimg.jp%2Falienty-pokemon%2Fimgs%2Ff%2F5%2Ff53e494b-s.png&w=200&h=200&output=webp&q=80","site_id":"pokemon_goh_doorblog_jp","site_name":"NEWSぽけまとめーる","category":"neta","hatena_bookmarks":0,"rank":4},{"id":"http://majimanjisokuhou.com/article/posttime-202604201900.html","title":"【画像】女児向けの漫画雑誌「りぼん」、地雷系向けになる","url":"http://majimanjisokuhou.com/article/posttime-202604201900.html","published":"2026-04-20T19:00:39+09:00","thumbnail":"https://wsrv.nl/?url=http%3A%2F%2Fmajimanjisokuhou.up.seesaa.net%2Fimage%2Fbook_zasshi_tana.png&w=200&h=200&output=webp&q=80","site_id":"majimanjisokuhou_com","site_name":"マジ卍速報","category":"neta","hatena_bookmarks":0,"rank":5},{"id":"https://shikaku105.blog.jp/archives/38284384.html","title":"田村ゆかりさんの過去一バイン〇イン＆胸チ〇ｗ","url":"https://shikaku105.blog.jp/archives/38284384.html","published":"2026-04-20T02:25:17+09:00","thumbnail":"https://wsrv.nl/?url=https%3A%2F%2Flivedoor.blogimg.jp%2Fshikaku105%2Fimgs%2F9%2Fb%2F9b85a88f.jpg&w=200&h=200&output=webp&q=80","site_id":"shikaku105_blog_jp","site_name":"2chNEWSまとめ","category":"neta","rank":6,"hatena_bookmarks":0},{"id":"https://pokemon-goh.doorblog.jp/archives/46029836.html","title":"【衝撃】80年代の女の子がガチで可愛いすぎるｗｗｗｗｗ(※画像あり)","url":"https://pokemon-goh.doorblog.jp/archives/46029836.html","published":"2026-04-20T06:18:08+09:00","thumbnail":"https://wsrv.nl/?url=https%3A%2F%2Flivedoor.blogimg.jp%2Falienty-pokemon%2Fimgs%2F4%2Fa%2F4a6e51e7-s.jpg&w=200&h=200&output=webp&q=80","site_id":"pokemon_goh_doorblog_jp","site_name":"NEWSぽけまとめーる","category":"neta","hatena_bookmarks":0,"rank":8},{"id":"https://netizen-voice.blog.jp/archives/47027195.html","title":"【悲報】笑点、2人やばそう","url":"https://netizen-voice.blog.jp/archives/47027195.html","published":"2026-04-20T19:00:03+09:00","thumbnail":"https://wsrv.nl/?url=https%3A%2F%2Flivedoor.blogimg.jp%2Fnetizen_reaction%2Fimgs%2F1%2F7%2F1706383a-s.jpg&w=200&h=200&output=webp&q=80","site_id":"netizen_voice_blog_jp","site_name":"ネラーボイス","category":"neta","hatena_bookmarks":0,"rank":9},{"id":"https://pokemon-goh.doorblog.jp/archives/46031666.html","title":"【衝撃】婚活歴11年のプロ婚活女子さん、希望年収を1000万円から800万円に下げてしまうｗｗｗｗｗ","url":"https://pokemon-goh.doorblog.jp/archives/46031666.html","published":"2026-04-20T13:18:09+09:00","thumbnail":"https://wsrv.nl/?url=https%3A%2F%2Flivedoor.blogimg.jp%2Falienty-pokemon%2Fimgs%2Fd%2Ff%2Fdf0789d3-s.png&w=200&h=200&output=webp&q=80","site_id":"pokemon_goh_doorblog_jp","site_name":"NEWSぽけまとめーる","category":"neta","hatena_bookmarks":0,"rank":11},{"id":"http://www.akb48matomemory.com/archives/1084171776.html","title":"【悲報】伊勢谷友が大麻に手を出した『理由』、ついに判明する・・・・・","url":"http://www.akb48matomemory.com/archives/1084171776.html","published":"2026-04-20T06:12:13+09:00","thumbnail":"https://wsrv.nl/?url=https%3A%2F%2Flivedoor.blogimg.jp%2Fakb48matomemory%2Fimgs%2F6%2F5%2F65f43612-s.jpg&w=200&h=200&output=webp&q=80","site_id":"www_akb48matomemory_com","site_name":"NEWSまとめもりー｜2chまとめブログ","category":"neta","hatena_bookmarks":0,"rank":12},{"id":"https://netizen-voice.blog.jp/archives/47023901.html","title":"小学生の息子(8)「調べれば出てくる事をわざわざ勉強する意味ってあるの？」","url":"https://netizen-voice.blog.jp/archives/47023901.html","published":"2026-04-20T04:00:11+09:00","thumbnail":null,"site_id":"netizen_voice_blog_jp","site_name":"ネラーボイス","category":"neta","rank":13,"hatena_bookmarks":0},{"id":"https://1000mg.jp/?p=247405","title":"【動画】アルゼンチンのラリーで観客が死亡する事故が発生してしまう。","url":"https://1000mg.jp/247405/","published":"Mon, 20 Apr 2026 13:00:41 +0000","thumbnail":"https://wsrv.nl/?url=https%3A%2F%2F1000mg.jp%2Fwp-content%2Fuploads%2F2026%2F04%2Fvideoframe_1876.jpg&w=200&h=200&output=webp&q=80","site_id":"1000mg_jp","site_name":"1000mg","category":"neta","hatena_bookmarks":0,"rank":14},{"id":"https://shikaku105.blog.jp/archives/38286560.html","title":"【画像】俺氏、資産が約1億円に到達ｗ","url":"https://shikaku105.blog.jp/archives/38286560.html","published":"2026-04-20T21:25:24+09:00","thumbnail":"https://wsrv.nl/?url=https%3A%2F%2Flivedoor.blogimg.jp%2Fshikaku105%2Fimgs%2F5%2F4%2F545b5e3a.jpg&w=200&h=200&output=webp&q=80","site_id":"shikaku105_blog_jp","site_name":"2chNEWSまとめ","category":"neta","hatena_bookmarks":0,"rank":15},{"id":"http://majimanjisokuhou.com/article/posttime-202604201130.html","title":"【画像】女優の山田優さん、インスタで水着姿を披露するも加工しすぎて足が変なことになってしまう","url":"http://majimanjisokuhou.com/article/posttime-202604201130.html","published":"2026-04-20T11:30:39+09:00","thumbnail":"https://wsrv.nl/?url=http%3A%2F%2Fmajimanjisokuhou.up.seesaa.net%2Fimage%2Fsp_05.png&w=200&h=200&output=webp&q=80","site_id":"majimanjisokuhou_com","site_name":"マジ卍速報","category":"neta","hatena_bookmarks":0,"rank":16},{"id":"https://1000mg.jp/?p=247375","title":"【動画】海上封鎖を破ったイラン船に攻撃する米軍のミサイル駆逐艦（USS Spruance）","url":"https://1000mg.jp/247375/","published":"Mon, 20 Apr 2026 10:00:25 +0000","thumbnail":"https://wsrv.nl/?url=https%3A%2F%2F1000mg.jp%2Fwp-content%2Fuploads%2F2026%2F04%2Fvideoframe_21947.jpg&w=200&h=200&output=webp&q=80","site_id":"1000mg_jp","site_name":"1000mg","category":"neta","hatena_bookmarks":0,"rank":17},{"id":"https://eegg.fun/text/20210907214326.html?ct=4","title":"とんでもない女に彼氏がロックオンされてしまった","url":"https://eegg.fun/text/20210907214326.html?ct=4","published":"2026-04-20T13:07:08+09:00","thumbnail":"https://wsrv.nl/?url=https%3A%2F%2Feegg.fun%2Fupfiles%2F20260420130638LjYGh.png&w=200&h=200&output=webp&q=80","site_id":"eegg_fun","site_name":"easterEgg","category":"life","hatena_bookmarks":0,"rank":1},{"id":"http://blog.livedoor.jp/news23vip/archives/6239161.html","title":"客「旅館の飯多すぎィ！今時どうなんやこれ」外野「全然多くない！残すな！」","url":"http://blog.livedoor.jp/news23vip/archives/6239161.html","published":"2026-04-18T00:00:47+09:00","thumbnail":"https://wsrv.nl/?url=https%3A%2F%2Flivedoor.blogimg.jp%2Fnews23vip%2Fimgs%2F4%2F1%2F41c546e0-s.png&w=200&h=200&output=webp&q=80","site_id":"blog_livedoor_jp_news23vip","site_name":"VIPPERな俺","category":"life","rank":2,"hatena_bookmarks":0},{"id":"http://matomelotte.com/archives/59805090.html","title":"今年のパ・リーグ、どこが優勝してもおかしくない大混戦","url":"http://matomelotte.com/archives/59805090.html","published":"2026-04-20T20:40:17+09:00","thumbnail":"https://wsrv.nl/?url=https%3A%2F%2Flivedoor.blogimg.jp%2Fvipperdeok-nelers%2Fimgs%2F3%2F6%2F3626b769-s.jpg&w=200&h=200&output=webp&q=80","site_id":"matomelotte_com","site_name":"まとめロッテ！","category":"sports","hatena_bookmarks":0,"rank":3},{"id":"http://blog.livedoor.jp/hawksmatome/archives/59805065.html","title":"正木智也がリハビリ順調　早期復帰目指す","url":"http://blog.livedoor.jp/hawksmatome/archives/59805065.html","published":"2026-04-20T20:31:25+09:00","thumbnail":"https://wsrv.nl/?url=https%3A%2F%2Flivedoor.blogimg.jp%2Fhawksmatome%2Fimgs%2F8%2Fc%2F8c09736d.jpg&w=200&h=200&output=webp&q=80","site_id":"blog_livedoor_jp_hawksmatome","site_name":"鷹速@ホークスまとめブログ","category":"sports","hatena_bookmarks":0,"rank":4},{"id":"http://blog.livedoor.jp/nanjmagnus/archives/59803493.html","title":"MLB、ストライク判定チャレンジを浪費させるために逆フレーミングが流行り出すwww","url":"http://blog.livedoor.jp/nanjmagnus/archives/59803493.html","published":"2026-04-20T07:00:20+09:00","thumbnail":"https://wsrv.nl/?url=https%3A%2F%2Flivedoor.blogimg.jp%2Fnanjmagnus%2Fimgs%2F4%2F8%2F48c6f817-s.jpg&w=200&h=200&output=webp&q=80","site_id":"blog_livedoor_jp_nanjmagnus","site_name":"なんＪは加速している","category":"sports","hatena_bookmarks":0,"rank":6},{"id":"https://basketballbbs.com/?p=176450","title":"【NBA】マレーの16本のフリースローは妥当か？判定を振り返る","url":"https://basketballbbs.com/nba/176450/","published":"Mon, 20 Apr 2026 09:10:26 +0000","thumbnail":null,"site_id":"basketballbbs_com","site_name":"バスケまとめ・COM","category":"sports","hatena_bookmarks":0,"rank":10},{"id":"http://blog.livedoor.jp/bbyakyu/ryusoku/dragons/63148512.html","title":"🐟山口一郎「ドラゴンズが勝った負けたで一喜一憂するのはバカだ」","url":"http://blog.livedoor.jp/bbyakyu/ryusoku/dragons/63148512.html","published":"2026-04-20T18:00:19+09:00","thumbnail":"https://wsrv.nl/?url=https%3A%2F%2Flivedoor.blogimg.jp%2Fbbyakyu%2Fimgs%2F5%2Ff%2F5f291c58-s.png&w=200&h=200&output=webp&q=80","site_id":"blog_livedoor_jp_bbyakyu","site_name":"竜速（りゅうそく）","category":"sports","hatena_bookmarks":0,"rank":11},{"id":"https://nofootynolife.net/blog-entry-8979.html","title":"ポルトガル人「日本は宝の山だ」守田英正、大一番でゴール！PK献上も名誉挽回！現地サポから称賛殺到！【海外の反応】","url":"https://nofootynolife.net/blog-entry-8979.html","published":"2026-04-20T10:47:46+09:00","thumbnail":"https://wsrv.nl/?url=https%3A%2F%2Fblog-imgs-184.fc2.com%2Fn%2Fo%2Ff%2Fnofootynolife%2F2026042010433736a.jpg&w=200&h=200&output=webp&q=80","site_id":"nofootynolife_net","site_name":"NO FOOTY NO LIFE","category":"sports","hatena_bookmarks":1,"rank":15},{"id":"http://blog.livedoor.jp/nanjstu/archives/63154985.html","title":"日本ハムファイターズチーム防御率4.24(12球団ワーストタイ)","url":"http://blog.livedoor.jp/nanjstu/archives/63154985.html","published":"2026-04-20T16:55:15+09:00","thumbnail":"https://wsrv.nl/?url=https%3A%2F%2Flivedoor.blogimg.jp%2Fnanjstu%2Fimgs%2Fe%2F6%2Fe6617914.jpg&w=200&h=200&output=webp&q=80","site_id":"blog_livedoor_jp_nanjstu","site_name":"なんじぇいスタジアム＠なんJまとめ","category":"sports","hatena_bookmarks":0,"rank":16},{"id":"http://matomelotte.com/archives/59804423.html","title":"パ・リーグ順位表(4月19日)ロッテ逆転勝利、オリ接戦制し同率首位","url":"http://matomelotte.com/archives/59804423.html","published":"2026-04-20T10:34:03+09:00","thumbnail":"https://wsrv.nl/?url=https%3A%2F%2Flivedoor.blogimg.jp%2Fvipperdeok-nelers%2Fimgs%2Fb%2F1%2Fb1164c95-s.jpg&w=200&h=200&output=webp&q=80","site_id":"matomelotte_com","site_name":"まとめロッテ！","category":"sports","hatena_bookmarks":0,"rank":17},{"id":"http://blog.livedoor.jp/nanjstu/archives/63152927.html","title":"村上の選球眼wwwwwwwwwwwwww","url":"http://blog.livedoor.jp/nanjstu/archives/63152927.html","published":"2026-04-19T15:11:44+09:00","thumbnail":"https://wsrv.nl/?url=https%3A%2F%2Flivedoor.blogimg.jp%2Fnanjstu%2Fimgs%2F1%2Fa%2F1ad88976-s.jpg&w=200&h=200&output=webp&q=80","site_id":"blog_livedoor_jp_nanjstu","site_name":"なんじぇいスタジアム＠なんJまとめ","category":"sports","hatena_bookmarks":0,"rank":19},{"id":"https://nogizakalife.tokyo/?p=202001","title":"【悲報】日向坂出会いましょうがつまらない","url":"https://nogizakalife.tokyo/?p=202001","published":"Sun, 19 Apr 2026 20:08:39 +0000","thumbnail":"https://wsrv.nl/?url=https%3A%2F%2Fnogizakalife.tokyo%2Fwp-content%2Fuploads%2F2026%2F04%2F0190_01-36-150x150.jpg&w=200&h=200&output=webp&q=80","site_id":"nogizakalife_tokyo_feed","site_name":"乃木坂LIFE -坂道・48高速まとめ-","category":"entame","hatena_bookmarks":0,"rank":2},{"id":"https://babymetalize.com/?p=87980","title":"村上宗隆がアスレチックス戦で3戦連発となる第8号ホームラン　【海外の反応】","url":"https://babymetalize.com/archives/87980","published":"Mon, 20 Apr 2026 03:00:17 +0000","thumbnail":null,"site_id":"babymetalize_com","site_name":"BABYMETALIZE","category":"entame","hatena_bookmarks":0,"rank":12},{"id":"http://46matome.net/archives/40313652.html","title":"【日向坂46】この企画、こんな神回になるとは...","url":"http://46matome.net/archives/40313652.html","published":"2026-04-20T17:40:48+09:00","thumbnail":"https://wsrv.nl/?url=https%3A%2F%2Flivedoor.blogimg.jp%2Fmatomato455-nogizaka46_3kisei%2Fimgs%2Fe%2F5%2Fe5bd19c3-s.jpg&w=200&h=200&output=webp&q=80","site_id":"46matome_net","site_name":"日向坂46まとめもり～","category":"entame","hatena_bookmarks":0,"rank":13},{"id":"https://geinou-7days.net/?p=61636","title":"小芝風花、29歳は“金髪お団子ヘア”で始動！「来年の今日」何かが起こる？【画像】","url":"https://geinou-7days.net/koshiba-fuka-blonde-hair-on-her-29th-birthday","published":"Mon, 20 Apr 2026 03:00:00 +0000","thumbnail":"https://wsrv.nl/?url=https%3A%2F%2Fgeinou-7days.net%2Fwp-content%2Fuploads%2F2025%2F01%2Fhair_kinpatsu_woman-150x150.png&w=200&h=200&output=webp&q=80","site_id":"geinou_7days_net","site_name":"芸能7days","category":"entame","hatena_bookmarks":0,"rank":14},{"id":"https://halospo.com/?p=3082","title":"【悲報】豫風瑠乃さん、ブログを辞めて10日以上が経過","url":"https://halospo.com/2026/04/20/post-3082/","published":"Mon, 20 Apr 2026 04:47:13 +0000","thumbnail":"https://wsrv.nl/?url=https%3A%2F%2Fs.w.org%2Fimages%2Fcore%2Femoji%2F17.0.2%2F72x72%2F1f410.png&w=200&h=200&output=webp&q=80","site_id":"halospo_com","site_name":"ハロスポ＠ハロプロまとめ","category":"entame","hatena_bookmarks":0,"rank":15},{"id":"http://nmb48-mtm.com/archives/59804539.html","title":"【NMB48】プロ野球女子会きたあああああ","url":"http://nmb48-mtm.com/archives/59804539.html","published":"2026-04-20T12:10:31+09:00","thumbnail":"https://wsrv.nl/?url=http%3A%2F%2Flivedoor.blogimg.jp%2Fnmb48matomeya%2Fimgs%2F6%2F2%2F62c12d68-s.jpg&w=200&h=200&output=webp&q=80","site_id":"nmb48_mtm_com","site_name":"NMB48まとめスピリッツ","category":"entame","hatena_bookmarks":0,"rank":16},{"id":"https://nogizakalife.tokyo/?p=202029","title":"【悲報】昨日の菅原キャプテンミーグリ待機人数、、、、、川崎さくたんとの比較","url":"https://nogizakalife.tokyo/?p=202029","published":"Mon, 20 Apr 2026 02:08:34 +0000","thumbnail":"https://wsrv.nl/?url=https%3A%2F%2Fnogizakalife.tokyo%2Fwp-content%2Fuploads%2F2026%2F04%2F0413_01-66-150x150.jpg&w=200&h=200&output=webp&q=80","site_id":"nogizakalife_tokyo_feed","site_name":"乃木坂LIFE -坂道・48高速まとめ-","category":"entame","hatena_bookmarks":0,"rank":18},{"id":"https://nogizakalife.tokyo/?p=202059","title":"AKB48劇場 5月1日～5月10日の公演スケジュールについて","url":"https://nogizakalife.tokyo/?p=202059","published":"Mon, 20 Apr 2026 06:31:53 +0000","thumbnail":"https://wsrv.nl/?url=https%3A%2F%2Fnogizakalife.tokyo%2Fwp-content%2Fuploads%2F2026%2F04%2F0649_01-72-150x150.jpg&w=200&h=200&output=webp&q=80","site_id":"nogizakalife_tokyo_feed","site_name":"乃木坂LIFE -坂道・48高速まとめ-","category":"entame","hatena_bookmarks":0,"rank":19},{"id":"http://46matome.net/archives/40311931.html","title":"【日向坂46】予告ですでに面白いw 次回ひなあい、約束された神回","url":"http://46matome.net/archives/40311931.html","published":"2026-04-20T07:00:48+09:00","thumbnail":"https://wsrv.nl/?url=https%3A%2F%2Flivedoor.blogimg.jp%2Fmatomato455-nogizaka46_3kisei%2Fimgs%2F6%2Fe%2F6eb2b7f8-s.jpg&w=200&h=200&output=webp&q=80","site_id":"46matome_net","site_name":"日向坂46まとめもり～","category":"entame","hatena_bookmarks":0,"rank":20}]}