{"schema_version":1,"updated_at":"2026-05-01T09:18:42.728765+00:00","hours_window":24,"categories":{"all":[{"rank":1,"word":"旭山動物園","search_keys":["動物","旭山動物園"],"count":26,"sample_titles":["旭川市長「旭川市と旭山動物園のイメージ低下や風評被害は非常に大きい」","旭山動物園が開業、焼却炉を見ようと100人以上が行列","【画像】旭山動物園の焼却炉で妻の死体を滅却した鈴木達也容疑者(33)のご尊顔・・・"]},{"rank":2,"word":"イランの最高指導者","search_keys":["イラン","イランの最高指導者"],"count":22,"sample_titles":["イランの最高指導者「核とミサイルの能力」を守ると発言…ホルムズ支配を放棄しない！","【速報】イランの最高指導者、最新コメントを発信","イランの最高指導者、「核とミサイルの能力」を守ると発言"]},{"rank":3,"word":"BeReal","search_keys":["BeReal"],"count":22,"sample_titles":["Z世代のBeRealテロが相次ぐ中、 完璧に使いこなしている女性がこちら！！","【悲報】BeReal女子、銀行内を投稿→顧客情報流出で謝罪＆株価にも影響する事態にｗｗｗ","【画像】BeReal、めちゃくちゃ酷い仕様だった。なんでやってるかも意味不明・・・"]},{"rank":4,"word":"高市早苗陣営","search_keys":["高市","高市早苗","高市早苗陣営"],"count":21,"sample_titles":["【衝撃】高市早苗陣営さん、匿名アカウントで高市礼賛動画を投稿していたｗｗｗｗｗｗｗｗｗｗ","【文春砲】高市早苗陣営、匿名アカウントで高市礼賛動画を投稿していた","【悲報】高市早苗陣営さん、匿名アカウントで礼賛動画を投稿していたとバレてしまう"]},{"rank":5,"word":"グラビア","search_keys":["グラビア"],"count":20,"sample_titles":["“インスタグラビアが大バズり”似鳥沙也加、仕上がったBODY披露","“アナ×グラビア”二刀流・瀧山あかねアナ、長身スレンダーボディから圧巻の美脚","【画像あり】令和のグラビア女王、あまりにも良いからみてくれ・・・"]},{"rank":6,"word":"中日ドラゴンズ","search_keys":["中日","中日ドラゴンズ"],"count":19,"sample_titles":["中日ドラゴンズ『魔の7回』、27戦で24失点","中日ドラゴンズ『魔の7回』、27戦で24失点","【悲報】中日ドラゴンズさん、8勝19敗で最下位なのに満員御礼が止まらないｗｗｗｗｗｗｗｗｗｗ"]},{"rank":7,"word":"職員","search_keys":["職員"],"count":18,"sample_titles":["【徳島県】契約書なしで草刈り委託　1400万円自腹の徳島県職員を懲戒免職","防衛省職員(27) 衝動に駆られた結果、○○していた女性宅に侵入して逮捕される","旭川市・旭山動物園「なんてことをしてくれたんだ」「旭川のイメージがまた…」地元は悲鳴「職員がベラベラしゃべっても…」  [5/1]"]},{"rank":8,"word":"福生マッチョハンマー男","search_keys":["ハンマー","ハンマー男","福生ハンマー男","福生マッチョハンマー男"],"count":17,"sample_titles":["【衝撃】福生マッチョハンマー男・高林輝行容疑者(44)の亡き父親、あの有名人だった！","≪指名手配・福生マッチョハンマー男≫ 亡き父親は有名プロ囲碁棋士・高林拓二氏 母親が語った“末っ子”の苦悩   |  ■金づち殴打逃走事件のまとめ","≪福生マッチョハンマー男≫亡き父親はプロ囲碁棋士「先物取引で失敗、借金が大変で」「彼女もいたけど仕事してないから結婚を許されず"]},{"rank":9,"word":"アメリカ","search_keys":["アメリカ"],"count":17,"sample_titles":["アメリカの富裕層「無料ニュースがフェイクだらけになっちゃった！」有料の新聞へ回帰の動き広がる","【衝撃動画】アメリカが凄すぎるｗｗｗｗこんな奴らがいるアメリカに戦争で勝てるわけないだろ…凄すぎる…","【悲報】アメリカ、また日本にタカりだす…"]},{"rank":10,"word":"焼却炉","search_keys":["焼却炉"],"count":17,"sample_titles":["旭山動物園が開業、焼却炉を見ようと100人以上が行列","【画像】旭山動物園の焼却炉で妻の死体を滅却した鈴木達也容疑者(33)のご尊顔・・・","【速報】道警、旭山動物園職員の鈴木達也容疑者(33)を逮捕 → 焼却炉から妻の遺体の一部が見つかり完全犯罪ならず"]},{"rank":11,"word":"グラドル","search_keys":["ドル","グラドル"],"count":17,"sample_titles":["【画像】化粧ノリが抜群な新生グラドル、オッサン達の鼻息が荒くなるｗｗｗｗ","声優・井口裕香、グラドル級ボディで『ヤングガンガン』表紙","【歓喜】若手グラドルたちが大集合！エロすぎて選びきれねぇｗｗｗｗ"]},{"rank":12,"word":"YouTuber","search_keys":["YouTube","YouTuber"],"count":17,"sample_titles":["【画像】ファッション系YouTuber「ダサい人、私がコーデし直します」→結果ｗｗｗｗ","月利50万のせどり系YouTuber、ホームセンターでシンナーやペイントうすめ液を大量に仕入れ・転売する動画で炎上","【大悲報】あの大人気YouTuber、新札を独占し炎上WWWWWWWWWWWWWWWWWWWWWWWWWWWWWWWWWWWWWWWWWWWWW"]},{"rank":13,"word":"玉川徹","search_keys":["玉川徹"],"count":17,"sample_titles":["【悲報】玉川徹氏、モーニングショーにて″倒れない″中国製ロボットを押し倒しポンコツである事を証明ｗｗｗｗｗｗ","玉川徹氏　テレ朝「モーニングショー」で“放送事故”、「押しても倒れない」はずの中国製の人型ロボットを押し倒し「やっちゃったよ」","【悲報】玉川徹さん、押して倒れない中国製人型ロボットを生放送で押し倒す"]},{"rank":14,"word":"確保","search_keys":["確保"],"count":16,"sample_titles":["福生市ハンマーおじさん、千葉県のアパートにて確保","【速報】ナフサ供給「年明け以降も確保」　代替調達進む　日本は6月で詰むとか言ってた奴ｗ","ナフサ供給「年明け以降も確保」　代替調達進む　日本は6月で詰むとか言ってた奴ｗ  [5/1]"]},{"rank":15,"word":"現役引退","search_keys":["引退","現役引退"],"count":16,"sample_titles":["【悲報】錦織圭さん、現役引退を発表してしまう","「格ゲー大会『獣道』で負けたら現役引退」を決めていたウメハラさん(44歳)、絶対負けたくない初心を思い出し現役続行を表明","【竜王戦】小倉久史八段が現役引退"]}],"news":[{"rank":1,"word":"旭山動物園","search_keys":["旭山動物園"],"count":15,"sample_titles":["旭川市長「旭川市と旭山動物園のイメージ低下や風評被害は非常に大きい」","旭山動物園が開業、焼却炉を見ようと100人以上が行列","旭川市民「旭山動物園で起きた事件のせいで、旭川のイメージがまた…。どんどん落ちていく」"]},{"rank":2,"word":"イランの最高指導者","search_keys":["イラン","イランの最高指導者"],"count":15,"sample_titles":["イランの最高指導者「核とミサイルの能力」を守ると発言…ホルムズ支配を放棄しない！","イランの最高指導者、「核とミサイルの能力」を守ると発言","イランの最高指導者、「核とミサイルの能力」を守ると発言   |  核て意味あるんかね  |  イランは長引かせてアメリカを破産させたいから終わらん"]},{"rank":3,"word":"高市早苗","search_keys":["高市","高市早苗"],"count":14,"sample_titles":["【文春砲】高市早苗陣営、匿名アカウントで高市礼賛動画を投稿していた","【文春砲】高市早苗陣営、匿名アカウントで高市礼賛動画と小泉・林アンチ動画を投稿していた","【工作活動】高市早苗陣営、犬笛どころか自ら匿名で岡田克也らを中傷するショート動画を投稿しまくっていたことがバレる！　公設第一秘書が依頼"]},{"rank":4,"word":"ドル円","search_keys":["ドル","ドル円"],"count":14,"sample_titles":["政府・日銀が為替介入！　ドル円が一瞬で160円→156円に","【速報】円、ついに156円台へ急騰…為替介入警戒でドル円がガチで荒れ始めるｗｗｗ","中卒「ドル円160円突破して高市積極財政で更に円が売られるんだよね？」"]},{"rank":5,"word":"ハンマー男","search_keys":["ハンマー","ハンマー男"],"count":12,"sample_titles":["【速報】逃亡中のハンマー男、千葉県のアパートで見つけ逮捕","【速報】福生ハンマー男、逮捕","【速報】福生市の逃走していたハンマー男、逮捕される"]},{"rank":6,"word":"職員","search_keys":["職員"],"count":12,"sample_titles":["【徳島県】契約書なしで草刈り委託　1400万円自腹の徳島県職員を懲戒免職","旭川市・旭山動物園「なんてことをしてくれたんだ」「旭川のイメージがまた…」地元は悲鳴「職員がベラベラしゃべっても…」  [5/1]","契約書なしで草刈りを委託した徳島県職員、懲戒免職　1400万円を自腹"]},{"rank":7,"word":"BeReal","search_keys":["BeReal"],"count":11,"sample_titles":["【悲報】BeReal女子、銀行内を投稿→顧客情報流出で謝罪＆株価にも影響する事態にｗｗｗ","【悲報】BeReal、めちゃくちゃ糞な仕様だった。なんでやってるかも意味不明","BeReal、教育現場でもトラブルに"]},{"rank":8,"word":"高市首相","search_keys":["高市首相"],"count":11,"sample_titles":["高市首相、イラン大統領と電話会談　全船舶の自由航行保障を申し入れ  [5/1]","高市首相がナフサ由来品｢年越し供給｣を表明､実像は⋯不足解消ではなく、輸入・精製・在庫・流通調整でつなぐ長期戦   |  もう備蓄は完了した？  |  完全になくなっても","【朗報】高市首相｢ナフサ､年明け以降も確保｣ 中東以外で代替調達"]},{"rank":9,"word":"確保","search_keys":["確保"],"count":10,"sample_titles":["福生市ハンマーおじさん、千葉県のアパートにて確保","【速報】ナフサ供給「年明け以降も確保」　代替調達進む　日本は6月で詰むとか言ってた奴ｗ","ナフサ供給「年明け以降も確保」　代替調達進む　日本は6月で詰むとか言ってた奴ｗ  [5/1]"]},{"rank":10,"word":"報道の自由","search_keys":["自由","報道の自由"],"count":10,"sample_titles":["海外「皮肉だ」報道の自由ランキングで日本が米国を上回ったことに海外びっくり仰天！（海外の反応）","報道の自由度ランキング、アジア最高位は台湾の28位　韓国47位、日本62位、中国178位、北朝鮮179位 [5/1]  [ばーど★]","報道の自由度ランキング　日本は180か国中62位　報道機関による「自己検閲が広まっている」と強調"]},{"rank":11,"word":"Amazon","search_keys":["Amazon"],"count":10,"sample_titles":["Amazon、楽天で見つけた特価品あれこれ","Amazonゴールデンウィーク スマイルSALE、とても静かに2日目突入【📦】","【朗報】Amazonゴールデンウィーク スマイルSALE、とても静かに2日目突入！！！！！"]},{"rank":12,"word":"中国製","search_keys":["中国製"],"count":9,"sample_titles":["日本人「中国製は品質がダメだから！ｗ」ワイ「品質が良くなったらどうすんの？」","中国製のEVバス、ハンドルを回すとブレーキホースが走行中のタイヤに接触しオイルが漏れる仕様に","【速報】スキー場の中国製エスカレーターで転倒した5歳児が窒息死　調査結果発表「安全装置を無効化していた」"]},{"rank":13,"word":"福生市","search_keys":["福生","福生市"],"count":9,"sample_titles":["福生市ハンマーおじさん、千葉県のアパートにて確保","【速報】福生市の逃走していたハンマー男、逮捕される","福生市のハンマー男･高林輝行容疑者､千葉県習志野市のアパートで逮捕｢殺すつもりはなかった｣"]},{"rank":14,"word":"旭川市","search_keys":["旭川","旭川市"],"count":9,"sample_titles":["旭川市長「旭川市と旭山動物園のイメージ低下や風評被害は非常に大きい」","旭川市・旭山動物園「なんてことをしてくれたんだ」「旭川のイメージがまた…」地元は悲鳴「職員がベラベラしゃべっても…」  [5/1]","旭川市長「旭川市と旭山動物園のイメージ低下や風評被害は非常に大きい」  [4/30]"]},{"rank":15,"word":"迎撃","search_keys":["迎撃"],"count":9,"sample_titles":["ウクライナ軍が水上ドローンから迎撃ドローンを発射し、空中のシャヘド無人機を撃墜！","日本のドローン開発企業、ウクライナで「シャヘド」迎撃に実戦で初成功！","【緊急】日本のドローン企業、ウクライナで迎撃成功…国産技術が実戦で証明されてしまうｗｗｗ"]}],"entame":[{"rank":1,"word":"グラビア","search_keys":["グラビア"],"count":17,"sample_titles":["“インスタグラビアが大バズり”似鳥沙也加、仕上がったBODY披露","“アナ×グラビア”二刀流・瀧山あかねアナ、長身スレンダーボディから圧巻の美脚","“ミニグラの超新星”池本しおり、勢い止まらずグラビア席巻"]},{"rank":2,"word":"写真集","search_keys":["写真集"],"count":5,"sample_titles":["元HKT48松本日向、人生最大露出に挑戦した1st写真集","女優・酒井若菜  45歳　13年ぶり写真集発売決定！（画像あり）","蓬莱舞、写真集未公開カット9枚を一挙解禁"]},{"rank":3,"word":"衣装","search_keys":["衣装"],"count":4,"sample_titles":["【にじさんじ】「栞葉るり」がハイクオリティフィギュア化！複雑な衣装や装飾も忠実に再現。フリューの高品質ホビーブランド『F:NEX』より『栞葉るり 1/7スケールフィギュア』","【にじさんじ】ローレン、軍服新衣装お披露目『かっこいいやんけ！！！！』『やっぱり黒赤が似合う男』『短髪ローレンもいいな』","【ぶいありうむ】にぃな、魔法学園衣装&新髪型お披露目『にぃなっぽさ失ってないしかわいいわ』『ボブカットイメージ変わるなぁ』"]},{"rank":4,"word":"ぱい","search_keys":["ぱい"],"count":4,"sample_titles":["【画像】上坂すみれの最新お●ぱいが流石にデカすぎる！これはもう誰も止めらんねええええええええ","【画像】Aマッソ加納、お●ぱいの形をくっきりさせてしまう！こんなにデカかったのかよ！","【最新画像】酒井若菜さん(45)のお●ぱい、建材だった！！！"]},{"rank":5,"word":"GW","search_keys":["GW"],"count":4,"sample_titles":["【にじさんじ】ミラン、GWに27→30万人達成までASMR耐久配信宣言","【ホロライブ】ししろん、GWにホロメンと動画形式のスペシャルコラボウィーク開催！【5/2-5/6(水-土)12時～】","【Vtuber】GWは金ビキニを着る期間という風潮"]},{"rank":6,"word":"お披露目","search_keys":["お披露目"],"count":4,"sample_titles":["【にじさんじ】ローレン、軍服新衣装お披露目『かっこいいやんけ！！！！』『やっぱり黒赤が似合う男』『短髪ローレンもいいな』","【ぶいありうむ】にぃな、魔法学園衣装&新髪型お披露目『にぃなっぽさ失ってないしかわいいわ』『ボブカットイメージ変わるなぁ』","【Vtuber】飴望にぃな新衣装お披露目！にぃなちゃん新衣装かわいいね"]},{"rank":7,"word":"露出","search_keys":["露出"],"count":4,"sample_titles":["元HKT48松本日向、人生最大露出に挑戦した1st写真集","【画像】韓アイドル、紅白でエロすぎな露出ショー、NHKどうした？wwww","国立大卒レースクイーン安藤笑、過去最大露出に挑戦"]},{"rank":8,"word":"挑戦","search_keys":["挑戦"],"count":4,"sample_titles":["元HKT48松本日向、人生最大露出に挑戦した1st写真集","元AKB48鈴木優香、物語仕立てグラビアに挑戦","【歓喜】声優・上坂すみれ、エロすぎるグラビアに挑戦ｗｗｗこれが日本のアニメ界かwwww"]},{"rank":9,"word":"櫻坂","search_keys":["櫻坂"],"count":4,"sample_titles":["櫻坂46山下瞳月、神秘的な美しさ放つグラビア","櫻坂46武元唯衣、卒業記念グラビアで7年半を回顧","【！？】櫻坂46、まさかのロケ企画が進行していた"]},{"rank":10,"word":"全盛期","search_keys":["全盛期"],"count":4,"sample_titles":["【画像】女の全盛期発見！これ見て腰振らないやつおる？wwwwww","【画像】程よく肉付き良い美人の全盛期、誰も気付いてないｗｗｗｗ","【動画】人妻MEGUMI、全盛期よりエロくなるwwwww"]},{"rank":11,"word":"卒業","search_keys":["卒業"],"count":4,"sample_titles":["櫻坂46武元唯衣、卒業記念グラビアで7年半を回顧","【悲報】陰キャワイ、高校も大学も童貞卒業ならず…その理由がこれｗｗｗ","【VTuber】紫式部、一身上の都合により卒業"]},{"rank":12,"word":"上坂","search_keys":["上坂"],"count":3,"sample_titles":["【画像】上坂すみれの最新お●ぱいが流石にデカすぎる！これはもう誰も止めらんねええええええええ","【画像】上坂すみれさん、デカすぎるｗｗｗｗｗ","【歓喜】声優・上坂すみれ、エロすぎるグラビアに挑戦ｗｗｗこれが日本のアニメ界かwwww"]},{"rank":13,"word":"高市","search_keys":["高市"],"count":3,"sample_titles":["【悲報】ヨドバシカメラ梅田、ペンタブ展示を再開した途端に「高市やめろ」と即落書きされる…","【悲報】安倍の遺志継ぐ高市さん、公文書問題で震えながら反論してしまうwwww","【悲報】高市大臣、「防衛増税」手のひらクルクルで評価するｗｗｗｗ"]},{"rank":14,"word":"制服","search_keys":["制服"],"count":3,"sample_titles":["【日向坂46】新制服、リボン組とネクタイ組の分け方って...【17thシングル】","【日向坂46】新制服、なかなか攻めてるな… メンバーの新ソロアー写が公開！","【日向坂46】新制服これまでより... 17thシングル個人アー写が更新！"]},{"rank":15,"word":"誹謗中傷","search_keys":["誹謗中傷"],"count":3,"sample_titles":["【ホロライブ】2025年度における誹謗中傷等の権利侵害行為に対する対応報告","【ななし】ハネマン麻雀63話「今VTuber界では空前の誹謗中傷ブーム!!」","【ホロライブ】カバー公式から2025年度における誹謗中傷等の権利侵害行為に対する対応報告"]}],"neta":[{"rank":1,"word":"ハンマーおじ","search_keys":["ハンマー","ハンマーおじ"],"count":15,"sample_titles":["【悲報】ハンマーおじが撃退した珍走団 住民は騒音で何百回も通報していた←これ！","【悲報】ハンマーおじが撃退した珍走団、住民は騒音で何百回も通報していた","【悲報】ハンマーおじさんが撃退した珍走団さん、住民は騒音で何百回も通報していたｗｗｗｗｗｗｗｗｗｗ"]},{"rank":2,"word":"高市早苗さん","search_keys":["高市","高市早苗","高市早苗さん"],"count":13,"sample_titles":["【画像】高市早苗さん、もうダメそう…","高市早苗さん、天皇ご臨席の式典で1人だけ子供のようにはしゃいでしまいTPO分からないと炎上","【悲報】高市早苗さん「暴力は世界のいかなる場所でも容認出来ない」→ 落語家にとんでもないことを言われてしまうｗｗｗｗｗｗｗｗｗｗ"]},{"rank":3,"word":"BeReal","search_keys":["BeReal"],"count":10,"sample_titles":["【画像】BeReal、めちゃくちゃ酷い仕様だった。なんでやってるかも意味不明・・・","【爆笑】BeRealとかいうデスゲーム参加型SNSｗｗｗｗｗｗｗｗｗｗ","【悲報】BeRealとかいうデスゲーム参加型SNS"]},{"rank":4,"word":"タモリ","search_keys":["タモリ"],"count":9,"sample_titles":["【伝説】タモリと黒柳徹子の『ベッドシーンのコント』、お腹ちぎれるwww","【芸能】粗品、ヒカルのタモリ発言に反論「人のことを“おもんない”とか“嫌い”って言うのはナンセンス」","【悲報】タモリさん、ガチで面白くないらしいｗｗｗｗｗｗｗｗｗｗ"]},{"rank":5,"word":"経過","search_keys":["経過"],"count":9,"sample_titles":["【画像】福生ハンマー男(44歳・ハゲ・実家暮らし)、逃走から40時間経過","【画像】スクエニさん、「FF7完全リメイク」を宣言してからもうすぐ11年が経過・・・","【画像】スクエニさん、「FF7完全リメイク」を宣言してからもうすぐ11年が経過・・・"]},{"rank":6,"word":"川上審判員","search_keys":["川上","川上審判員"],"count":8,"sample_titles":["【悲報】ヤクルト・オスナのバット直撃の川上審判員、2週間経ってもまだ意識回復しない模様・・・","【悲報】ヤクルト・オスナのバット直撃の川上審判員、2週間経ってもまだ意識回復せず・・・","【プロ野球】NPBがバット頭部直撃の川上審判員の状況を説明 集中治療室から一般病棟へ まだ意識は回復せず「懸命な治療とリハビリを継続"]},{"rank":7,"word":"一般病棟","search_keys":["一般病棟"],"count":8,"sample_titles":["バット直撃の川上拓斗球審（30）　一般病棟に移るも意識は","【プロ野球】NPBがバット頭部直撃の川上審判員の状況を説明 集中治療室から一般病棟へ まだ意識は回復せず「懸命な治療とリハビリを継続","【野球】バットが頭部直撃の川上審判員、集中治療室から一般病棟へ　まだ意識は回復せず"]},{"rank":8,"word":"アメリカ","search_keys":["アメリカ"],"count":8,"sample_titles":["アメリカの富裕層「無料ニュースがフェイクだらけになっちゃった！」有料の新聞へ回帰の動き広がる","【悲報】アメリカ、また日本にタカりだす…","【悲報】日本人さん「アメリカとガチで戦って友情が芽生えた」外国人「原爆落とされ侵略されただけやん」ｗｗｗｗｗｗｗｗｗｗ"]},{"rank":9,"word":"Z世代","search_keys":["Z世代"],"count":8,"sample_titles":["【悲報】Z世代さん、イスラム教への改宗ブームが起きてしまう","【衝撃】Z世代新卒さん、職場の写真をSNSにアップした結果ｗｗｗｗｗ(※画像あり)","【悲報】Z世代、マジでどうしようもないゴミ世代確定へwwwwww"]},{"rank":10,"word":"ホルムズ海峡","search_keys":["ホルムズ海峡"],"count":8,"sample_titles":["中国、『日本籍タンカーが中国元でホルムズ海峡通航料を支払った』というデマを流す","トランプ大統領「ホルムズ海峡ではなくトランプ海峡と呼ぶべき」","【画像】本日のトランプ「ホルムズ海峡ではなくトランプ海峡と呼ぶべきだ」"]},{"rank":11,"word":"襲撃","search_keys":["襲撃"],"count":8,"sample_titles":["【画像】ハンマーでガキや警察を襲撃した男、暴走族から母親を守るためだったwwwwwwwww","【画像】ハンマーでガキや警察を襲撃した男、暴走族から母親を守るためだったwwwwwwwww","【悲報】移住YouTuber「りん」、村の男たちに襲撃されそうになる…その理由がコレｗｗｗｗ"]},{"rank":12,"word":"玉川徹","search_keys":["玉川徹"],"count":8,"sample_titles":["【悲報】玉川徹氏、モーニングショーにて″倒れない″中国製ロボットを押し倒しポンコツである事を証明ｗｗｗｗｗｗ","【悲報】玉川徹さん、押して倒れない中国製人型ロボットを生放送で押し倒す","玉川徹氏　テレ朝「モーニングショー」で“放送事故”、「押しても倒れない」はずの中国製の人型ロボットを押し倒し「やっちゃったよ」"]},{"rank":13,"word":"YouTuber","search_keys":["YouTuber"],"count":8,"sample_titles":["【大悲報】あの大人気YouTuber、新札を独占し炎上WWWWWWWWWWWWWWWWWWWWWWWWWWWWWWWWWWWWWWWWWWWWW","月利50万のせどり系YouTuber、ホームセンターでシンナーやペイントうすめ液を大量に仕入れ・転売する動画で炎上","【衝撃】女性せどりYouTuber、ついに『一線』を超えてしまう・・・・・・"]},{"rank":14,"word":"鈴木福","search_keys":["鈴木福"],"count":8,"sample_titles":["【画像】鈴木福くんの『運転免許証』、ガチでヤバイｗｗｗｗｗｗｗｗｗ","俳優・鈴木福　運転免許証を取得「ちゃんとMTだよ」報告に驚きの声「AT限定じゃないだと…！？」「イカす」","【悲報】鈴木福さん「運転免許を取得しました！！ちゃんとMTだよ」ｗｗｗｗｗｗｗｗｗｗ"]},{"rank":15,"word":"旭山動物園","search_keys":["動物","旭山動物園"],"count":7,"sample_titles":["【画像】旭山動物園の焼却炉で妻の死体を滅却した鈴木達也容疑者(33)のご尊顔・・・","【悲報】旭山動物園で妻を焼いた鈴木達也容疑者(33)、笑顔で出勤してその後も動物を焼却していた","【画像】旭山動物園の焼却炉で妻の死体を滅却した鈴木達也容疑者(33)のご尊顔・・・"]}],"life":[{"rank":1,"word":"筋トレ","search_keys":["筋トレ"],"count":6,"sample_titles":["【朗報】168cm体重56kgで毎日筋トレとランニングして食事してプロテイン飲んでいたらwwwwwwwww","【画像】筋トレ一年生なんやけど、この体見てほしい","筋トレ1日1時間でいいってマジかｗｗｗｗｗｗ"]},{"rank":2,"word":"明日","search_keys":["明日"],"count":4,"sample_titles":["福間香奈女流五冠、明日記者会見を行う予定","明日1日(金)は警報級の大雨や強風　長距離移動は時間に余裕を持って　道路影響予測","【悲報】明日キャンプ行くけど晩飯どうするか迷ってる"]},{"rank":3,"word":"cm","search_keys":["cm"],"count":3,"sample_titles":["【朗報】168cm体重56kgで毎日筋トレとランニングして食事してプロテイン飲んでいたらwwwwwwwww","【画像】平均的な日本のアラサー女子（154cm/61.7kg/38%/29歳）の体型がこちらｗｗｗｗ","【画像】識者『肛門に”4cm以上のもの”を入れるとこうなる』⇒！！"]},{"rank":4,"word":"プロテイン","search_keys":["プロテイン"],"count":3,"sample_titles":["【朗報】168cm体重56kgで毎日筋トレとランニングして食事してプロテイン飲んでいたらwwwwwwwww","【ネタ】Q：プロテインは太るって本当？　A：太るのはプロテインじゃなくて君です。","プロテイン飲んでるのに全く痩せないんだが…"]},{"rank":5,"word":"食べ物","search_keys":["食べ物"],"count":3,"sample_titles":["ひろゆき氏「食べ物を粗末にしてる人が食文化を語っても説得力が減る」","アンチエイジングのいい食べ物","旅先でガッカリしたこと、もの（人、食べ物、宿泊、観光等）"]},{"rank":6,"word":"在庫","search_keys":["在庫"],"count":3,"sample_titles":["【タイムセール】AppleWatchやAirPodsなどがセール中！iPhone、MacBook、iPadなど在庫アリ（セール対象外）！","【不動産】都心マンション価格高騰に急ブレーキ…「売れない在庫」急増で“転売不動産バブル崩壊”前夜を思わせる不気味な兆候","ポリエチレンなどの国内在庫は1.8カ月分、3月生産8.6％減＝経産省"]}],"sports":[{"rank":1,"word":"中日","search_keys":["中日"],"count":16,"sample_titles":["【ドラゴンズ実況】5/1 中日vs広島（マツダ）18:00～先発：柳【中継:Jスポ1】","中日球団関係者「ビジターでは盛り塩しません」","中日バンテリンドームで塩むすび発売wwwwwwwwwwwwwwwwwwwwwwwwwwwwwwwww"]},{"rank":2,"word":"DeNA","search_keys":["DeNA"],"count":7,"sample_titles":["先制弾＆決勝打の大暴れDeNAヒュンメル、ひげそり効果にニンマリ「ナイスシェイブ…流行になるのかな」　相川監督も「ずっと、そっとけって話」","DeNA2年目の篠木健太郎が６回２失点プロ初勝利「持ち味のストレートで勝負できた」　相川監督も称賛","【試合結果】 4/30　中日 2-6 DeNA 7回マラー、メヒア捕まり勝ち越しを許し痛い連敗 借金11"]},{"rank":3,"word":"大谷","search_keys":["大谷"],"count":6,"sample_titles":["【悲報】小学生大谷翔平、カービィとワンピースが好きだった","【悲報】大谷翔平さん、今年あと全部中5日で平均6イニング投げないと規定投球回に到達しない模様","【悲報】大谷翔平、MLB打者ランキングでトップ10位圏外ｗｗｗｗｗｗｗｗｗｗｗｗｗｗｗｗｗｗｗｗｗｗｗｗｗｗ"]},{"rank":4,"word":"絶賛","search_keys":["絶賛"],"count":6,"sample_titles":["堂安律、ドイツ地元紙が絶賛「チームを救った」絶妙ゴール＆守備でも「常に危険な存在」","英紙が1G1Aの鎌田大地を「ショーを独占」と大絶賛！ 退団濃厚の報道に現地パレスサポ悲鳴wwwww","「1年半ぶりのゴールがここで出るとか主人公すぎるだろ」イングランド人、鎌田大地を大絶賛ｗｗｗｗ"]},{"rank":5,"word":"ゴール","search_keys":["ゴール"],"count":6,"sample_titles":["堂安律、ドイツ地元紙が絶賛「チームを救った」絶妙ゴール＆守備でも「常に危険な存在」","【サッカー】上田綺世の移籍に〝暗雲〟 強豪相手に無得点で「彼のゴールに価値があるか」と地元メディア","「1年半ぶりのゴールがここで出るとか主人公すぎるだろ」イングランド人、鎌田大地を大絶賛ｗｗｗｗ"]},{"rank":6,"word":"阪神","search_keys":["阪神"],"count":6,"sample_titles":["昨日のヤクルトvs阪神の乱闘未遂、木澤のオラつき投法","阪神佐藤輝明　打率1位 本塁打1位タイ 打点1位","【ヤクルト対阪神6回戦】阪神がヤクルトに大勝し首位堅守！今季最多16安打で10得点 佐藤輝が森下に並ぶ7号＆タイムリー 小幡4安打 岡城プロ初猛打賞 西勇5回2失点で2年ぶり白星"]},{"rank":7,"word":"OPS","search_keys":["OPS"],"count":5,"sample_titles":["OPS.708っぽい選手","吉田正尚(ゴ) .265 0本 5打点 OPS.717 WAR0.1","ヨルダン・アルバレス　.356 12本 27打点 OPS1.199"]},{"rank":8,"word":"日本ハム","search_keys":["日本ハム"],"count":5,"sample_titles":["日本ハムVSオリックス　加藤 貴之が先発　試合実況　inエスコンF　18:00〜","日本ハム・新庄剛志監督　早くも交流戦でセ・リーグ相手に白星荒稼ぎ宣言「そういう予感がします」","日本ハム・新庄剛志監督　早くも交流戦でセ・リーグ相手に白星荒稼ぎ宣言「そういう予感がします」"]},{"rank":9,"word":"巨人","search_keys":["巨人"],"count":5,"sample_titles":["巨人は〝八回の男〟大勢不在で首位・阪神戦へ　甲子園遠征帯同させず4日ヤクルト戦で復帰目指す　阿部監督明かす","巨人・橋上オフェンスチーフ、ダルベックがベンチ外で「打線としては難しいメンバーに」　阪神戦へメンバー入れ替え示唆","【逆転負け】巨人ファン集合"]},{"rank":10,"word":"鎌田大地","search_keys":["鎌田大地"],"count":5,"sample_titles":["英紙が1G1Aの鎌田大地を「ショーを独占」と大絶賛！ 退団濃厚の報道に現地パレスサポ悲鳴wwwww","「1年半ぶりのゴールがここで出るとか主人公すぎるだろ」イングランド人、鎌田大地を大絶賛ｗｗｗｗ","【朗報】鎌田大地無双！ECL準決勝で決勝点含む1G1A!! パレス史上初&自身2度目の欧州タイトルへｗｗｗｗｗｗｗ"]},{"rank":11,"word":"MLB","search_keys":["MLB"],"count":5,"sample_titles":["バウアー、悲しい告白「MLB球団にこちらからオファーを出したんだ。タダでもいい。何でもやる」","【悲報】大谷翔平、MLB打者ランキングでトップ10位圏外ｗｗｗｗｗｗｗｗｗｗｗｗｗｗｗｗｗｗｗｗｗｗｗｗｗｗ","佐々木朗希投手、MLBナンバー1に輝く"]},{"rank":12,"word":"川上","search_keys":["川上"],"count":5,"sample_titles":["【速報】頭にバット直撃の川上球審、意識戻らず・・・・","選手会・近藤健介会長が川上拓斗球審へコメント","プロ野球選手会、バット直撃の川上球審に緊急声明発表"]},{"rank":13,"word":"勝ち越し","search_keys":["勝ち越し"],"count":5,"sample_titles":["日本ハム、延長の末逆転勝ち＆2カードぶり勝ち越し！11回野村がV打！","【西武対日本ハム6回戦】日本ハム、延長11回表1アウト一三塁からから野村佑希のタイムリーで勝ち越し！！！！！！！！！！！！","【巨人対広島5回戦】広島が坂倉将吾の逆転３ランで９カードぶり勝ち越し！開幕３連勝以来　８回２死からチーム２安打目が強烈な一撃に　７回２死までノーノー許す"]},{"rank":14,"word":"ACLE","search_keys":["ACLE"],"count":4,"sample_titles":["【サッカー】ACLE、町田　悲願アジア王者まであと一歩…数的有利も“完全アウェー洗礼”延長戦で敗れ無念の準優勝","【サッカー】ACLE   26ー27年から出場枠24→32に拡大　日本勢は３チームが本大会から／国別枠一覧","サウジ集中開催となったACLEは不公平？アル・アハリの連覇に英紙は「日本で試合をしなければならなかったとしたら…」"]},{"rank":15,"word":"白星","search_keys":["白星"],"count":4,"sample_titles":["日本ハム・新庄剛志監督　早くも交流戦でセ・リーグ相手に白星荒稼ぎ宣言「そういう予感がします」","日ハム新庄監督　早くも交流戦でセ・リーグ相手に白星荒稼ぎ宣言「そういう予感がします」","日本ハム・新庄剛志監督　早くも交流戦でセ・リーグ相手に白星荒稼ぎ宣言「そういう予感がします」"]}],"anige":[{"rank":1,"word":"Switch","search_keys":["Switch"],"count":7,"sample_titles":["【悲報】なぜSwitch2ではサードが売れないのか…","Switch「エルミナージュ ORIGINAL～闇の巫女と神々の指輪～」 2882本","Switch2　プラグマタ　14453本"]},{"rank":2,"word":"ポケモン","search_keys":["ポケモン"],"count":7,"sample_titles":["ポケモンのミニリュウ、逝く","ガキの頃ワイ「ポケモン赤緑発売！おはスタ放送スタート！コロコロ！」","【悲報】昔のポケモン、難易度高すぎる"]},{"rank":3,"word":"ガンダム","search_keys":["ガンダム"],"count":6,"sample_titles":["【速報】ガンダム声優の黒沢ともよさん、第一子出産をご報告","※『ガンダムvs.シリーズ』の新作にプレイアブル機体として参戦できそうな量産型ＭＳを集めるスレ","【驚愕】名作『ガンダム』凄い事に気付いたｗｗｗｗガンダムの階級なんだけど…もしかして「アムロ」と「ブライト」は…"]},{"rank":4,"word":"黒沢ともよ","search_keys":["黒沢ともよ"],"count":4,"sample_titles":["【速報】ガンダム声優の黒沢ともよさん、第一子出産をご報告","【祝】声優の黒沢ともよさんが第一子を出産！！","【祝】声優・黒沢ともよさんが第一子を出産"]},{"rank":5,"word":"Vtuber","search_keys":["Vtuber"],"count":4,"sample_titles":["【速報】イギリスのVtuber、自身が描いた自画イラスト画像のせいで逮捕されるwww","【速報】ぶいすぽ運営、謹慎処分したVtuberの疑惑についてお気持ち表明「特定の活動者様が関与される事実は一切ありません」","【朗報】元ホロライブVtuberの火威青(青くゆ)、転生したと話題に！？"]},{"rank":6,"word":"任天堂","search_keys":["任天堂"],"count":4,"sample_titles":["オタク「エアライドの新作出せ?」 任天堂「わーったよ、ほら出したよ？」","Switch2で\"前例のない\"症状が発生→任天堂「見せてほしい」「点検させてほしい」とめっちゃ前のめりに→実際の画面がこちら","YouTubeの株ポケ非公式「ポケモンの生態紹介動画」チャンネル、任天堂の申し立てで閉鎖"]},{"rank":7,"word":"ソシャゲ","search_keys":["ソシャゲ"],"count":4,"sample_titles":["【悲報】新作中華ソシャゲ、ゲーム内の広告が｢天気の子｣の画像を生成AIに食わせていることが話題になり大荒れ","【悲報】ソシャゲ掛け持ち、結局3つくらいが限界ｗｗｗｗ","「ハマってたソシャゲのアカウントが無期限停止にされた。まじ意味分からん」 → 最悪の原因が判明・・・"]},{"rank":8,"word":"リメイク","search_keys":["リメイク"],"count":4,"sample_titles":["サンソフト、ルート16のリメイク『ROUTE16R』発表。もちろんあのハードはハブられる。","【悲報】スクエニさん、「FF7完全リメイク」を宣言してからもうすぐ11年が経過","【画像】Switch2版「FF7リメイク」家の中から物が消える Σ (`･ω･´)！！"]},{"rank":9,"word":"劇場版","search_keys":["劇場版"],"count":4,"sample_titles":["【凄い】『劇場版 魔法少女まどか☆マギカ〈ワルプルギスの廻天〉』新PV公開！！","ソードアート・オンライン完全新作オリジナル劇場版制作中","【凄い】『劇場版 魔法少女まどか☆マギカ〈ワルプルギスの廻天〉』新PV公開！！"]},{"rank":10,"word":"魔法少女","search_keys":["魔法少女"],"count":4,"sample_titles":["【凄い】『劇場版 魔法少女まどか☆マギカ〈ワルプルギスの廻天〉』新PV公開！！","【凄い】『劇場版 魔法少女まどか☆マギカ〈ワルプルギスの廻天〉』新PV公開！！","『劇場版 魔法少女まどか☆マギカ〈ワルプルギスの廻天〉』新PV公開！　新たな魔法少女のCVは若山詩音さん、黒沢ともよさん"]},{"rank":11,"word":"ワンピース","search_keys":["ワンピース"],"count":4,"sample_titles":["【朗報】ワンピースのスピンオフ作品、うっかり初週28万部売れてしまうｗｗｗｗｗｗｗｗｗｗｗｗｗｗｗｗｗｗｗｗｗｗｗｗｗｗｗ","【衝撃】ワンピース史上最悪の後付け設定、とうとうガチ決まるｗｗｗｗ","【衝撃】ワンピースのマリンフォード頂上戦争編、フィクションの最高傑作だったｗｗｗ"]},{"rank":12,"word":"プラグマタ","search_keys":["プラグマタ"],"count":3,"sample_titles":["カプコンの海外公式Xアカウントを次々ハッキングする『プラグマタ』のディアナ、ついにあの新作ゲームの発売日を突き止めてしまうｗｗｗｗｗ","Switch2　プラグマタ　14453本","【4/20～4/26 ファミ通週販】「トモコレ わくわく生活」が2週連続1位！Switch２版「プラグマタ」「エルミナージュ」もランクイン！！"]},{"rank":13,"word":"第一子","search_keys":["第一子"],"count":3,"sample_titles":["【速報】ガンダム声優の黒沢ともよさん、第一子出産をご報告","【祝】声優の黒沢ともよさんが第一子を出産！！","【祝】声優・黒沢ともよさんが第一子を出産"]},{"rank":14,"word":"ドラゴン","search_keys":["ドラゴン"],"count":3,"sample_titles":["ドラゴンボールのピッコロって作中一番の常識人じゃね？","『ドラゴンボール』【驚愕】天才科学者「ドクター・ゲロ」とんでもない事が判明するｗｗｗｗ「ドクター・ゲロ」が…怖すぎる…","【悲報】ドラゴンボール孫悟飯さん、何故父さんを超えられなかったのかｗｗｗｗ"]},{"rank":15,"word":"Z世代","search_keys":["Z世代"],"count":3,"sample_titles":["Z世代のBeRealテロが相次ぐ中、 完璧に使いこなしている女性がこちら！！","【悲報】Z世代のゲームの「遊び方」、信じられない・・・・・・","【悲報】Z世代銀行員、職場の写真をSNSにアップし大炎上→銀行謝罪へｗｗｗｗ"]}]},"popular":[{"rank":1,"word":"通過","search_keys":["通過"],"count":3,"sample_titles":["出光のタンカーがホルムズ海峡通過　イラン大使館「出光の日章丸は両国間の友情の証」","韓国人「日本の出光のタンカーがホルムズ海峡を通過、日本政府が交渉し通航料も払ってない模様」→「韓国にもやってくれよ」「韓国とイランは仲が悪いから・・・」「これは100％裏でお金を払ってるか何かしてあげたんだろう」","【速報】「親日反民族行為者財産還収法」改正案が通過　帝国に加担した子孫の財産や所有権を強制売却"]},{"rank":2,"word":"由来","search_keys":["由来"],"count":2,"sample_titles":["武漢ウイルスは中国・武漢の研究所からの漏洩に由来することを正式に公に認める  [4/30]","高市首相、ナフサ由来の化学製品を年越えて供給継続できる見込み"]},{"rank":3,"word":"出光","search_keys":["出光"],"count":2,"sample_titles":["出光のタンカーがホルムズ海峡通過　イラン大使館「出光の日章丸は両国間の友情の証」","韓国人「日本の出光のタンカーがホルムズ海峡を通過、日本政府が交渉し通航料も払ってない模様」→「韓国にもやってくれよ」「韓国とイランは仲が悪いから・・・」「これは100％裏でお金を払ってるか何かしてあげたんだろう」"]},{"rank":4,"word":"イラン","search_keys":["イラン"],"count":2,"sample_titles":["韓国人「日本の出光のタンカーがホルムズ海峡を通過、日本政府が交渉し通航料も払ってない模様」→「韓国にもやってくれよ」「韓国とイランは仲が悪いから・・・」「これは100％裏でお金を払ってるか何かしてあげたんだろう」","【速報】米軍幹部がトランプ大統領にイラン攻撃計画説明"]},{"rank":5,"word":"現役","search_keys":["現役"],"count":2,"sample_titles":["【衝撃】12年も現役だったゲームボーイってヤバくね","【考察】AKB30周年コンサートの現役メンバー予想"]},{"rank":6,"word":"戸塚ヨットスクール","search_keys":["戸塚ヨットスクール"],"count":2,"sample_titles":["戸塚ヨットスクールが想像より凄かった","【衝撃】戸塚ヨットスクールが想像より凄かった・・・・・"]},{"rank":7,"word":"乃木坂","search_keys":["乃木坂"],"count":2,"sample_titles":["【衝撃】乃木坂公式が今年の全国ツアーの座長をバラしてしまう😱😨😰","【画像】高校時代の高市が乃木坂顔負けの美少女な件"]}]}