{"schema_version":1,"updated_at":"2026-04-22T10:52:45.142509+00:00","hours_window":24,"categories":{"all":[{"rank":1,"word":"イラン","search_keys":["イラン"],"count":34,"sample_titles":["イラン国会議長「脅されての交渉受け入れず」－戦場でのカード準備","トランプ大統領はイランに対して核兵器の使用を阻止されたか？","【国際】トランプ氏、イランとの「停戦延長」　協議終了まで　封鎖は継続"]},{"rank":2,"word":"ヒカキン","search_keys":["ヒカキン"],"count":34,"sample_titles":["【朗報】ヒカキンの麦茶、メルカリで売れまくる。ガチのお小遣いチャンスだそこれ、急げっ","【速報】ヒカキンのONICHA、転売されまくるｗｗｗｗｗｗｗｗｗｗ","【速報】ヒカキンのONICHA、転売されまくるｗw"]},{"rank":3,"word":"麦茶","search_keys":["麦茶"],"count":29,"sample_titles":["【朗報】ヒカキンの麦茶、メルカリで売れまくる。ガチのお小遣いチャンスだそこれ、急げっ","【画像】HIKAKINの麦茶、メルカリで滅茶苦茶にされる","【悲報】ヒカキンさんの麦茶、何故かメルカリで高額転売される事態にｗｗｗｗｗｗｗｗｗｗ"]},{"rank":4,"word":"タモリ","search_keys":["タモリ"],"count":27,"sample_titles":["「タモリさんって全く面白くない」ヒカルの“芸人批判”にネット不快感","YouTuberヒカル「タモリって全く面白くないよね」→結果、驚愕の事態に発展してしまうｗｗｗｗ","【悲報】「タモリさんって全く面白くない」YouTuberヒカルの芸人批判にネット不快感「ある程度の教養が無いと面白く感じないかもですね」"]},{"rank":5,"word":"高市内閣","search_keys":["高市","高市内閣"],"count":25,"sample_titles":["高市内閣「公務員が使うIT機器は政府が認めたメーカーの製品しか認めません」","【春季例大祭】城内経済財政相が靖国神社を参拝　高市内閣の閣僚で初！！","高市内閣支持、微減59.1％　過去最低も高水準維持　時事世論調査"]},{"rank":6,"word":"ONICHA","search_keys":["ONICHA"],"count":25,"sample_titles":["【速報】ヒカキンのONICHA、転売されまくるｗｗｗｗｗｗｗｗｗｗ","【速報】ヒカキンのONICHA、転売されまくるｗw","【画像】スーツ氏「ONICHAはありがたい。鶴瓶の麦茶の美味しさに気づかせてくれたから。」"]},{"rank":7,"word":"戦車","search_keys":["戦車"],"count":24,"sample_titles":["なぜ10式戦車で暴発事故は起きたのか？…元陸将が指摘する「障害物」「強度不足」の懸念！","ハイテク戦車で何が 防衛省に衝撃   #陸自4人死傷 |  射撃訓練の時上司殺した陸自もいたよな","陸上自衛隊「10式戦車」が訓練中に爆発事故、3人死亡1人重傷　装置の不具合や人的ミスの可能性も含めて調査"]},{"rank":8,"word":"NHK","search_keys":["NHK"],"count":23,"sample_titles":["【実況】MLB『ドジャース vs ジャイアンツ』 山本由伸先発、大谷翔平スタメン　NHK BS　10：45～","【悲報】NHKを解約したかった男性、『完全終了』のお知らせ・・・","NHK『うたコン』生放送ドタバタ《歌謡ミュージカル》　FRUITS ZIPPER＆MAZZELが新人社員役で最新曲披露"]},{"rank":9,"word":"トランプ大統領","search_keys":["トランプ","トランプ大統領"],"count":21,"sample_titles":["トランプ大統領はイランに対して核兵器の使用を阻止されたか？","トランプ大統領の支持率、ついに危険水域に突入か　イラン戦争と経済悪化で支持率大幅ダウン…","【悲報】トランプ大統領、イランを爆撃する気満々。停戦期限切れで23日に火蓋が切られる模様・・・"]},{"rank":10,"word":"しゃぶ葉","search_keys":["しゃぶ葉"],"count":20,"sample_titles":["【朗報】しゃぶ葉の肉、めちゃめちゃ分厚くなるwwwwwwwwwwwwwwwwwwww","【画像】しゃぶ葉の肉、めちゃめちゃ分厚くなるｗｗｗｗｗ","【画像あり】肉が薄すぎた「しゃぶ葉」、謝罪した翌日の肉がこちらｗｗｗｗ"]},{"rank":11,"word":"中日ドラゴンズ","search_keys":["中日","中日ドラゴンズ"],"count":19,"sample_titles":["【悲報】中日ドラゴンズ、20試合消化時点で逆転負け10の投壊ｗｗｗｗｗ","【悲報】中日ドラゴンズ、20試合消化時点で逆転負け10の投壊ｗｗｗｗｗ","中日ドラゴンズ「4勝16敗 勝率.200」←これについての率直な感想"]},{"rank":12,"word":"武器輸出解禁","search_keys":["輸出","武器輸出","武器輸出解禁"],"count":19,"sample_titles":["高市首相、武器輸出解禁「時代変わった」…専門家「平和国家捨て去った」！","「高市は一線を超えた」「我々の税金が人殺しに…」 殺傷能力武器輸出解禁を音楽家が懸念","「高市は一線を超えた」「我々の税金が人殺しに…」殺傷能力武器輸出解禁を音楽家が懸念"]},{"rank":13,"word":"ニコニコ動画","search_keys":["ニコニコ動画"],"count":18,"sample_titles":["ニコニコ動画、AIがコメントしてくれる実験機能を追加　動画上にも流れる","ニコニコ動画、実験機能「AIキャラクターコメント」を提供開始","【朗報】ニコニコ動画、『AI盛り上げ隊』を導入して過疎化対策を図る"]},{"rank":14,"word":"カ月","search_keys":["カ月"],"count":18,"sample_titles":["辺野古転覆から1カ月超、沖縄・玉城知事が現場近くで献花「落ち着くタイミング待った」   |  毎日新聞「転覆したのは漁船」","DAZN、サッカープランが登場 3カ月間980円のキャンペーン開始 （※ 年間総額2万6340円）サッカーW杯全試合視聴可能   |  大切なこと","【悲報】ネカフェで他人のセッ◯スを10回盗撮した自衛隊員、停職4カ月"]},{"rank":15,"word":"高市首相","search_keys":["高市首相"],"count":18,"sample_titles":["高市首相が靖国神社に真榊奉納一瞬で中国が反応する","高市首相、武器輸出解禁「時代変わった」…専門家「平和国家捨て去った」！","日本政府、あっさりと武器輸出を全面解禁→高市首相に非難殺到　凄まじい規模でネット大論争に"]}],"news":[{"rank":1,"word":"イラン","search_keys":["イラン"],"count":27,"sample_titles":["トランプ大統領はイランに対して核兵器の使用を阻止されたか？","【国際】トランプ氏、イランとの「停戦延長」　協議終了まで　封鎖は継続","ベッセント財務長官「カーグ島の原油貯蔵施設は数日で満杯、イランの油田は生産停止に追い込まれる」"]},{"rank":2,"word":"戦車","search_keys":["戦車"],"count":17,"sample_titles":["なぜ10式戦車で暴発事故は起きたのか？…元陸将が指摘する「障害物」「強度不足」の懸念！","ハイテク戦車で何が 防衛省に衝撃   #陸自4人死傷 |  射撃訓練の時上司殺した陸自もいたよな","陸上自衛隊「10式戦車」が訓練中に爆発事故、3人死亡1人重傷　装置の不具合や人的ミスの可能性も含めて調査"]},{"rank":3,"word":"高市首相","search_keys":["高市","高市首相"],"count":16,"sample_titles":["高市首相、武器輸出解禁「時代変わった」…専門家「平和国家捨て去った」！","【悲報】高市首相、「外交が難しい」と弱音を吐く","高市首相、武器輸出「時代変わった」　専門家「平和国家捨て去った」"]},{"rank":4,"word":"不足","search_keys":["不足"],"count":15,"sample_titles":["なぜ10式戦車で暴発事故は起きたのか？…元陸将が指摘する「障害物」「強度不足」の懸念！","「ナフサ」不足、主要頂点の石油化学製品メーカー52社、サプライチェーン4万6741社で　電気・自動車・住宅・衣料・医療・食品","【朝日世論調査】中東情勢で生活必需品が不足する不安「感じる」82%"]},{"rank":5,"word":"武器輸出解禁","search_keys":["輸出","武器輸出","武器輸出解禁"],"count":14,"sample_titles":["高市首相、武器輸出解禁「時代変わった」…専門家「平和国家捨て去った」！","「高市は一線を超えた」「我々の税金が人殺しに…」 殺傷能力武器輸出解禁を音楽家が懸念","「高市は一線を超えた」「我々の税金が人殺しに…」　殺傷能力武器輸出解禁を音楽家が懸念  [冬月記者★]"]},{"rank":6,"word":"停戦延長","search_keys":["停戦","停戦延長"],"count":12,"sample_titles":["【国際】トランプ氏、イランとの「停戦延長」　協議終了まで　封鎖は継続","【国際】トランプ氏、イランとの「停戦延長」　協議終了まで　封鎖は継続","【為替相場】トランプ大統領が停戦延長を発表　一瞬振動が走るも基本的な円売り傾向に変化なし　原油は昨日からやや上昇"]},{"rank":7,"word":"辺野古転覆","search_keys":["辺野古","辺野古転覆"],"count":11,"sample_titles":["辺野古転覆から1カ月超、沖縄・玉城知事が現場近くで献花「落ち着くタイミング待った」   |  毎日新聞「転覆したのは漁船」","「人としてどうなのか」国民・玉木氏、遺族に謝罪なきヘリ基地反対協を疑問視　辺野古転覆","「人としてどうなのか」国民・玉木氏、遺族に謝罪なきヘリ基地反対協を疑問視 辺野古転覆"]},{"rank":8,"word":"トランプ大統領","search_keys":["トランプ","トランプ大統領"],"count":11,"sample_titles":["トランプ大統領はイランに対して核兵器の使用を阻止されたか？","トランプ大統領の支持率、ついに危険水域に突入か　イラン戦争と経済悪化で支持率大幅ダウン…","トランプ大統領、米国が拿捕したイラン関連船に「中国からの贈り物だ。少し驚いた」　武器示唆か"]},{"rank":9,"word":"国会","search_keys":["国会"],"count":11,"sample_titles":["【ﾈｯﾄで話題】東京マラソンスタート地点の3.6万人 ｖｓ 国会前デモの3.6万人の画像を比較した結果 → ｗｗｗｗｗｗｗｗｗｗｗｗｗｗｗｗｗｗｗｗｗｗｗｗｗ","「国家情報局」新設法案、今国会で成立公算大 国民民主が賛成の方針   |  統一協会は国家情報局に睨まれる前に解散できて良かったんじゃないのw","【マジキチ】共産党信者、護憲デモと東京マラソンの比較画像に「この2枚で何の比較になるんだ」と勝利宣言…ネット「じゃあ国会前デモでその規模どこにあるの？」"]},{"rank":10,"word":"ナフサ","search_keys":["ナフサ"],"count":11,"sample_titles":["「ナフサ」不足、主要頂点の石油化学製品メーカー52社、サプライチェーン4万6741社で　電気・自動車・住宅・衣料・医療・食品","日経平均、一時過去最高値を更新 史上初の6万円に迫る   #株価 |  ナフサ供給問題で、あらゆることがエラいことになってるのに","【悲報】「ナフサ」不足、主要頂点の石油化学製品メーカー52社、サプライチェーン4万6741社で　電気・自動車・住宅・衣料・医療・食品"]},{"rank":11,"word":"狭小住宅","search_keys":["住宅","狭小住宅"],"count":10,"sample_titles":["【悲報】政府、国の計画から住宅の最小限の面積を定める「最低居住面積水準」を削除へ　「狭小住宅が若い世代に人気だからいいっしょｗ」","人気の「狭小住宅」 国の計画から「最低居住面積水準」削除に | NHK","人気の「狭小住宅」 国の計画から「最低居住面積水準」削除に | NHK"]},{"rank":12,"word":"ヒカキン","search_keys":["ヒカキン"],"count":9,"sample_titles":["【朗報】ヒカキンの麦茶、メルカリで売れまくる。ガチのお小遣いチャンスだそこれ、急げっ","ヒカキン「日本の麦茶、変えるぞ！」と豪語も、「ONICHA」が“普通の味”だった驚く背景…麦茶で「本格」や「高級」をうたうことは難しい","【ざまぁ】ヒカキンが生んだ日本を変えるはずのワクワク麦茶『ONICHA』、転売ヤーが大量に転売するも全く売れず大爆死ｗｗｗｗｗ"]},{"rank":13,"word":"原油","search_keys":["原油"],"count":9,"sample_titles":["ベッセント財務長官「カーグ島の原油貯蔵施設は数日で満杯、イランの油田は生産停止に追い込まれる」","メキシコのシェインバウム大統領､余剰原油の日本輸出を発表 量については未知数","シェインバウム大統領 余剰原油の日本輸出を明らかに   #メキシコ |  ありがたいけどさ。"]},{"rank":14,"word":"麦茶","search_keys":["麦茶"],"count":8,"sample_titles":["【朗報】ヒカキンの麦茶、メルカリで売れまくる。ガチのお小遣いチャンスだそこれ、急げっ","ヒカキン「日本の麦茶、変えるぞ！」と豪語も、「ONICHA」が“普通の味”だった驚く背景…麦茶で「本格」や「高級」をうたうことは難しい","【画像】スーツ氏「ONICHAはありがたい。鶴瓶の麦茶の美味しさに気づかせてくれたから。」"]},{"rank":15,"word":"ニコニコ動画","search_keys":["ニコニコ動画"],"count":8,"sample_titles":["ニコニコ動画、実験機能「AIキャラクターコメント」を提供開始","【朗報】ニコニコ動画、ＡＩがコメントしてくれる画期的な機能を実装！","ニコニコ動画、AIがコメントしてくれる実験機能を追加・・・"]}],"entame":[{"rank":1,"word":"初配信","search_keys":["初配信"],"count":10,"sample_titles":["【にじさんじ】御子神琴音、初配信の実況感想まとめ『エリート令嬢ストリーマーライバーや』『スプラ日本1位！？』『ローレンセット完食！？』【Y4T4】","【にじさんじ】レヨン、初配信の実況感想まとめ『スト6マスター(3日)LoLダイヤ3(2年)valo元日本一(5年)』『ガチのゲーム特化タイプやん』『意外とかわいい系の声やった』【Y4T4】","【にじさんじ】小々波いるか、初配信の実況感想まとめ『お絵かき！バイク！ゴルフ！LOL！』『語尾の伸ばし方にソフィア味を感じる』『多趣味な中でLoLだけ異質』【Y4T4】"]},{"rank":2,"word":"安達","search_keys":["安達"],"count":5,"sample_titles":["【週刊文春】安達結希くんの母親が衝撃告白「絶対に犯人は一人じゃない。共犯者がいるとしか思えない」","【新潮砲】安達優季容疑者(37)に悲しき過去「母は祖母に子を託すと、すぐさま姿を消した」","【週刊新潮】安達優季容疑者(37)に衝撃的な新潮砲が炸裂！子どもの学年を聞かれた結果…"]},{"rank":3,"word":"にじさんじ","search_keys":["にじさんじ"],"count":5,"sample_titles":["【にじさんじ】塚原大地、初配信の実況感想まとめ『ヴァロメインか』『揚げ鶏さん』『良い声の無駄遣いこそにじさんじやな』【Y4T4】","【にじさんじ】UHA味覚糖× #にじさんじ 第3弾コラボ、始動――。今回のテーマは『 にじ満腹ミッション』。","【にじさんじ】「にじさんじのTOYBOX！」、出演者の体調不良により放送日程を変更"]},{"rank":4,"word":"シングル","search_keys":["シングル"],"count":4,"sample_titles":["【NMB48】33rdシングル「タイトル未定」劇場盤「オンライン個別お話し会」追加枠対象メンバーがこちら","【日向坂46】おひさま、17thシングル収録内容に驚く【Kind of love】","【日向坂46】新たに8名が全完売！17thシングルのミーグリ2次完売表がこちら"]},{"rank":5,"word":"ミーグリ","search_keys":["ミーグリ"],"count":4,"sample_titles":["【日向坂46】こんなに！？ミーグリ完売枠、前作からの伸びが凄すぎる...【17thシングル Kind of love】","【櫻坂46】3名に新完売枠！櫻坂46ミーグリ『第11次受付』完売表がこちら【14thシングル The growing up train】","【日向坂46】とんでもない事になってる...ミーグリ『第2次受付』完売表がこちら【17thシングル Kind of love】"]},{"rank":6,"word":"17th","search_keys":["17th"],"count":3,"sample_titles":["【日向坂46】おひさま、17thシングル収録内容に驚く【Kind of love】","【日向坂46】新たに8名が全完売！17thシングルのミーグリ2次完売表がこちら","【日向坂46】三期生曲に末っ子マリン楽曲も！17thシングルの収録内容が判明！！"]},{"rank":7,"word":"天気","search_keys":["天気"],"count":3,"sample_titles":["NHKラジオのお天気お姉さん（45)「こんなおばさんだけど、いいの？」（画像あり）","【画像】ﾃﾞｶﾊﾟｲお天気お姉さんｗｗｗｗｗ","【画像】可愛くて巨乳なお天気お姉さん！"]},{"rank":8,"word":"結希","search_keys":["結希"],"count":3,"sample_titles":["【週刊文春】安達結希くんの母親が衝撃告白「絶対に犯人は一人じゃない。共犯者がいるとしか思えない」","【週刊文春】安達結希くんの母親にとんでもない文春砲が炸裂してしまう！","【悲報】結希くんの母親、憔悴しきってしまう"]},{"rank":9,"word":"ONICHA","search_keys":["ONICHA"],"count":3,"sample_titles":["【画像】スーツ氏「ONICHAはありがたい。鶴瓶の麦茶の美味しさに気づかせてくれたから。」","【速報】ヒカキンのONICHA、転売されまくるｗｗｗｗｗｗｗｗｗ（画像あり）","【悲報】ヒカキンのONICHA、転売されまくるｗｗｗｗｗ"]},{"rank":10,"word":"琴音","search_keys":["琴音"],"count":3,"sample_titles":["【にじさんじ】御子神琴音、初配信の実況感想まとめ『エリート令嬢ストリーマーライバーや』『スプラ日本1位！？』『ローレンセット完食！？』【Y4T4】","【にじさんじ】琴音「ゲームやってドカ食いして寝るのが一番気持ち良い」","【にじさんじ】御子神琴音初配信！ローレンセットしたんか！？"]},{"rank":11,"word":"優季","search_keys":["優季"],"count":3,"sample_titles":["【新潮砲】安達優季容疑者(37)に悲しき過去「母は祖母に子を託すと、すぐさま姿を消した」","【週刊新潮】安達優季容疑者(37)に衝撃的な新潮砲が炸裂！子どもの学年を聞かれた結果…","【衝撃】安達優季容疑者の偽装工作、初日から崩壊していた！覆面パトカーに尾行されると猿芝居"]},{"rank":12,"word":"Day","search_keys":["Day"],"count":3,"sample_titles":["【雀魂大大大大大大大感謝杯7th】Day2 ぐみひゃく春のスカウト祭！星川四暗刻うおおおおおおおお","【にじさんじ】歌ってみたリレーDay1！歌上手くね？","【にじさんじ】本日、4/21(火)21:00から初配信リレーDay1開始！初配信後は歌ってみたリレーDay1も開始！"]},{"rank":13,"word":"タモリ","search_keys":["タモリ"],"count":3,"sample_titles":["【爆弾発言】「タモリさんって全く面白くない」YouTuberヒカルの芸人批判にネット不快感「ある程度の教養が無いと面白く感じないかもですね」","「タモリさんって全く面白くない」YouTuberヒカルの“芸人批判”にネット不快感…「ある程度の教養が無いと面白く感じないかもですね」","Youtuberヒカル「タモリさんって全く面白くない」芸人批判にネットは不快感"]}],"neta":[{"rank":1,"word":"ヒカキン","search_keys":["ヒカキン"],"count":18,"sample_titles":["【速報】ヒカキンのONICHA、転売されまくるｗｗｗｗｗｗｗｗｗｗ","【速報】ヒカキンのONICHA、転売されまくるｗw","【悲報】ヒカキンさんの麦茶、何故かメルカリで高額転売される事態にｗｗｗｗｗｗｗｗｗｗ"]},{"rank":2,"word":"高市首相","search_keys":["高市","高市首相"],"count":17,"sample_titles":["高市首相が靖国神社に真榊奉納一瞬で中国が反応する","【悲報】高市首相さん、「外交が難しい」とガチで弱音吐いてしまう・・・・・・・・・","【悲報】高市首相さん、「外交が難しい」と弱音吐く"]},{"rank":3,"word":"麦茶","search_keys":["麦茶"],"count":15,"sample_titles":["【画像】HIKAKINの麦茶、メルカリで滅茶苦茶にされる","【悲報】ヒカキンさんの麦茶、何故かメルカリで高額転売される事態にｗｗｗｗｗｗｗｗｗｗ","【悲報】ヒカキン麦茶、メルカリで売れまくる"]},{"rank":4,"word":"NHK","search_keys":["NHK"],"count":15,"sample_titles":["【実況】MLB『ドジャース vs ジャイアンツ』 山本由伸先発、大谷翔平スタメン　NHK BS　10：45～","【悲報】NHKを解約したかった男性、『完全終了』のお知らせ・・・","NHKあしたが変わるトリセツショー「ネコ」のトリセツ　科学とヒトと劇場で…　4月23日 木曜 19:30 ム"]},{"rank":5,"word":"しゃぶ葉","search_keys":["しゃぶ葉"],"count":14,"sample_titles":["【朗報】しゃぶ葉の肉、めちゃめちゃ分厚くなるwwwwwwwwwwwwwwwwwwww","【画像】しゃぶ葉の肉、めちゃめちゃ分厚くなるｗｗｗｗｗ","【画像あり】肉が薄すぎた「しゃぶ葉」、謝罪した翌日の肉がこちらｗｗｗｗ"]},{"rank":6,"word":"タモリ","search_keys":["タモリ"],"count":14,"sample_titles":["YouTuberヒカル「タモリって全く面白くないよね」→結果、驚愕の事態に発展してしまうｗｗｗｗ","【悲報】「タモリさんって全く面白くない」YouTuberヒカルの芸人批判にネット不快感「ある程度の教養が無いと面白く感じないかもですね」","「タモリさんって全く面白くない」ヒカルの“芸人批判”にネット不快感"]},{"rank":7,"word":"辺野古","search_keys":["辺野古"],"count":11,"sample_titles":["毎日新聞「辺野古沖で転覆したのは漁船」","【衝撃】山口恵以子さん「京都小学生殺人は1日6時間報道、辺野古転覆事故は1週間で38分」・・・・・・・・・","辺野古転覆から1カ月超、沖縄・玉城知事が現場近くで献花「落ち着くタイミング待った」"]},{"rank":8,"word":"カ月","search_keys":["カ月"],"count":11,"sample_titles":["【悲報】ネカフェで他人のセッ◯スを10回盗撮した自衛隊員、停職4カ月","辺野古転覆から1カ月超、沖縄・玉城知事が現場近くで献花「落ち着くタイミング待った」","辺野古転覆から1カ月超、沖縄・玉城デニー知事が現場近くで献花「落ち着くタイミング待った」"]},{"rank":9,"word":"京都","search_keys":["京都"],"count":11,"sample_titles":["【衝撃】山口恵以子さん「京都小学生殺人は1日6時間報道、辺野古転覆事故は1週間で38分」・・・・・・・・・","【悲報】京都小学生殺人の報道は1日6時間、辺野古転覆事故は1週間で38分だった模様","【芸能】でか美ちゃん、京都男児遺棄事件を受けて 「うちはお兄ちゃんが連れ子…偏見が強まらなければいいな」"]},{"rank":10,"word":"ガンダム","search_keys":["ガンダム"],"count":11,"sample_titles":["【画像】実写ガンダム(Netflix)のキャストｗｗｗｗ","【悲報】Netflix実写版「ガンダム」さん、メインキャスト正式発表されるも嫌な予感しかしない","【悲報】実写ガンダム(Netflix)のキャストwwwwwwwwwwwwwwwwwwww"]},{"rank":11,"word":"YouTuberヒカル","search_keys":["YouTuber","YouTuberヒカル"],"count":10,"sample_titles":["YouTuberヒカル「タモリって全く面白くないよね」→結果、驚愕の事態に発展してしまうｗｗｗｗ","【悲報】「タモリさんって全く面白くない」YouTuberヒカルの芸人批判にネット不快感「ある程度の教養が無いと面白く感じないかもですね」","【炎上】YouTuberヒカル「タモリさんって全く面白くない」に批判殺到ｗｗｗ"]},{"rank":12,"word":"Netflix","search_keys":["Netflix"],"count":10,"sample_titles":["【画像】実写ガンダム(Netflix)のキャストｗｗｗｗ","【悲報】Netflix実写版ガンダムさん、どう考えてもケツアゴシャアになってしまう・・・・・・・・・","【悲報】Netflix実写版「ガンダム」さん、メインキャスト正式発表されるも嫌な予感しかしない"]},{"rank":13,"word":"ONICHA","search_keys":["ONICHA"],"count":9,"sample_titles":["【速報】ヒカキンのONICHA、転売されまくるｗｗｗｗｗｗｗｗｗｗ","【速報】ヒカキンのONICHA、転売されまくるｗw","【悲報】ヒカキンさんの新作麦茶「ONICHA」、鶴瓶以下だと話題にｗｗｗｗｗｗｗｗｗｗ"]},{"rank":14,"word":"権利","search_keys":["権利"],"count":9,"sample_titles":["【悲報】NHKを見ない権利、裁判で否定される・・・","地裁、NHK受信料支払い命令　「見ない権利」主張の男性に","名古屋地裁、NHK放送を「見ない権利」主張の男性に受信料全額の支払いを命じる　テレビを手放さず解約認められず"]},{"rank":15,"word":"武器輸出","search_keys":["輸出","武器輸出"],"count":8,"sample_titles":["【悲報】日本さん、武器輸出を全面解禁で『死の商人』デビューしてしまう","【朗報】日本の武器輸出規制、緩和","「5類型」撤廃、武器輸出を緩和　護衛艦やミサイルの輸出可能に"]}],"life":[{"rank":1,"word":"筋トレ","search_keys":["筋トレ"],"count":6,"sample_titles":["【悲報】43歳の筋トレ男さん、なぜかフェミオバサン達に叩かれる","筋トレしてる人が食べる炭水化物は白米でも大丈夫？","筋トレはジムより自宅トレーニングの方が良い点しかなくない？"]},{"rank":2,"word":"ミリオンゴッド","search_keys":["ミリオンゴッド"],"count":4,"sample_titles":["【新台】ユニバ「Lミリオンゴッド神々の軌跡」5ch実戦感想＆評価まとめ！「夢を見るなら吉宗、懐古に浸るならGOD」「ホールの貯金箱」等","ユニバ「Lミリオンゴッド神々の軌跡」サウンドトラックの配信がスタート！","パチンコ・スロットの中古価格一覧が公開！ミリオンゴッドは160万円超え！"]},{"rank":3,"word":"ご飯","search_keys":["ご飯"],"count":3,"sample_titles":["「ウインナーだとご飯が進まない」家族のわがまま発言に厳しい声　「嫌なら自分で作れ」「贅沢な悩み」","大根おろしがけご飯はなぜ理解されないのか","【料理】朝食にウインナーをだしたら「ウインナーだとご飯が進まない」と家族に言われたのですが"]},{"rank":4,"word":"邪神","search_keys":["邪神"],"count":3,"sample_titles":["【新台】三洋「L邪神ちゃんドロップキック」速報動画が公開！","【新台】SANYO「パチスロ邪神ちゃんドロップキック」速報ムービー公開！超人気の神コンテンツが禁断のパチスロ化","【朗報】パチスロ邪神ちゃんドロップキックリリース記念「SANYO本社襲撃イベント・パチサバト」参加者募集がスタート！合法的にSANYOに進入するCHANCEだぞー"]},{"rank":5,"word":"パチスロ","search_keys":["パチスロ"],"count":3,"sample_titles":["パチスロの『相性』ってなんなの？これがある限り純粋にパチスロ楽しめないよ","【新台】SANYO「パチスロ邪神ちゃんドロップキック」速報ムービー公開！超人気の神コンテンツが禁断のパチスロ化","【朗報】パチスロ邪神ちゃんドロップキックリリース記念「SANYO本社襲撃イベント・パチサバト」参加者募集がスタート！合法的にSANYOに進入するCHANCEだぞー"]},{"rank":6,"word":"ダイエット","search_keys":["ダイエット"],"count":3,"sample_titles":["【疑問】太ってる人はなぜ「よし、そろそろダイエットしよう」にならないの？","今年からダイエット始めて","ダイエットを始めてから食べ物の栄養に注意するようになり、いろいろ気づかされた…"]},{"rank":7,"word":"お菓子","search_keys":["お菓子"],"count":3,"sample_titles":["柳月のお菓子セット初めて注文してみた","コーヒーと相性のいいお菓子、推薦お願いします","合わなかったお菓子ありますか？"]},{"rank":8,"word":"ユニバ","search_keys":["ユニバ"],"count":3,"sample_titles":["【新台】ユニバ「Lミリオンゴッド神々の軌跡」5ch実戦感想＆評価まとめ！「夢を見るなら吉宗、懐古に浸るならGOD」「ホールの貯金箱」等","ユニバ「Lミリオンゴッド神々の軌跡」サウンドトラックの配信がスタート！","【新台】ユニバ「Lミリオンゴッド-神々の軌跡-」感想・評判まとめ！通常時アメグレは脳汁ヤバすぎ！複数万枚＆コンプリート報告あり"]},{"rank":9,"word":"麦茶","search_keys":["麦茶"],"count":3,"sample_titles":["【悲報】ヒカキンの麦茶、全然売れてない","【朗報】ヒカキンプロデュースの麦茶\"ONICHA\"、鬼ウマイ！！！","ヒカキンさんプロデュース「ONICHA」発売、「普通の麦茶」トレンド入り　フリマアプリ転売も"]},{"rank":10,"word":"食べ放題","search_keys":["食べ放題"],"count":3,"sample_titles":["【カスハラ？】鳥貴族、『食べ放題（未就学児は無料）』で3歳児から料金とろうとして炎上　店長「未就学児とは0～2歳」","こないだ初めて焼肉食べ放題の店行ったんやけどさ","【朗報】焼肉ライク、9時間食べ放題開始"]}],"sports":[{"rank":1,"word":"中日ドラゴンズ","search_keys":["中日","中日ドラゴンズ"],"count":15,"sample_titles":["中日ドラゴンズ「4勝16敗 勝率.200」←これについての率直な感想","【悲報】中日ドラゴンズ、20試合消化時点で逆転負け10","【悲報】中日ドラゴンズ、20試合消化時点で逆転負け10の投壊WWWWWWWWWWWWWWWWWWWWWWWWWWWWWW"]},{"rank":2,"word":"巨人","search_keys":["巨人"],"count":11,"sample_titles":["【巨人対中日5回戦】巨人・石塚、2回裏2アウト一三塁からプロ初打点となる2点タイムリースリーベース！！！！！！！！！！！！！！！！","【巨人対中日5回戦】巨人、2回裏1アウト一三塁から佐々木俊輔のタイムリーで先制！！！！！！！！！","【ドラゴンズ実況】4/22 中日vs巨人（前橋）18:00～先発：櫻井【中継:BS日テレ　日テレG+ DAZN他】"]},{"rank":3,"word":"阪神","search_keys":["阪神"],"count":10,"sample_titles":["【ハマスタ花火大会】DeNA・佐野恵太、阪神・茨木から第2号同点ソロホームラン！！！！！！！！！！！！！！！！【DeNA対阪神5回戦】","【ハマスタの王】阪神・大山、二打席連発となる第3号逆転満塁ホームラン！！！！！！！！！！！！！！！！！！！！！【DeNA対阪神5回戦】","【DeNA対阪神5回戦】阪神・大山、DeNA・竹田から第２号ソロホームラン！！！！！！！！！！！！！！！"]},{"rank":4,"word":"ロッテ","search_keys":["ロッテ"],"count":9,"sample_titles":["【ロッテ対オリックス5回戦】オリックス・紅林、ロッテ・毛利から第3号勝ち越し3ランホームラン！！！！！！！！！！！！！！！","一軍試合実況　4月22日18:00～ ロッテ－オリックス(毛利×曽谷)","ロッテが得点圏打数飛び抜けてリーグ1位なんだけどこれマジ？"]},{"rank":5,"word":"村上宗隆","search_keys":["村上宗隆"],"count":8,"sample_titles":["シカホワ村上宗隆、バレル率メジャー全体3位","【朗報】村上宗隆さん、アーロン・ジャッジと肩を並べるwwwwwwwwwwwwwwwwww","漫画・村上宗隆物語で13番目ぐらいに人気になりそうなキャラｗｗｗｗｗｗｗｗｗｗｗｗｗｗｗｗｗｗｗｗｗｗｗｗｗｗｗｗｗｗｗｗｗ"]},{"rank":6,"word":"DeNA","search_keys":["DeNA"],"count":8,"sample_titles":["【ハマスタ花火大会】DeNA・佐野恵太、阪神・茨木から第2号同点ソロホームラン！！！！！！！！！！！！！！！！【DeNA対阪神5回戦】","【DeNA対阪神5回戦】DeNA・牧の守備…","【DeNA対阪神5回戦】阪神・大山、DeNA・竹田から第２号ソロホームラン！！！！！！！！！！！！！！！"]},{"rank":7,"word":"三笘薫","search_keys":["三笘薫"],"count":7,"sample_titles":["三笘薫、攻守で躍動！ブライトンはチェルシーに3-0完勝しEL出場圏内の6位に浮上","【GIF】三笘薫さん、決まったらプスカシュ賞クラスの超絶ゴラッソクラスの惜しいシュートをチェルシー戦で放つｗｗｗｗｗ","【朗報】ブライトン三笘薫…強豪チェルシーにも活躍し完勝してしまうｗｗｗｗｗ"]},{"rank":8,"word":"OPS","search_keys":["OPS"],"count":6,"sample_titles":["秋山翔吾(広).263(19-5)1本2打点OPS.789","大谷翔平(32) .271(85-23) 5本 11打点 1盗塁 得点圏.158 OPS.890←率直な感想","【悲報】GO!松本さん、打率.226 0本 2打点 OPS.526"]},{"rank":9,"word":"ACLE","search_keys":["ACLE"],"count":5,"sample_titles":["サウジ人「日本はアジア最強だ」日本勢、4年連続ACLE決勝進出！人材の宝庫ぶりにサウジアラビア人から尊敬と嘆きの声！【海外の反応】","J1町田、VARに2度救われACLE初参戦で史上初の決勝進出！相馬先制弾でシャバブ・アルアハリ撃破！（関連まとめ）","【サッカー】FC町田ゼルビアが初出場でクラブ史上初のACLE決勝進出！ 相馬の決勝点で接戦を制す｜AFCチャンピオンズリーグエリート"]},{"rank":10,"word":"守備","search_keys":["守備"],"count":5,"sample_titles":["【巨人対中日5回戦】中日の守備…","【DeNA対阪神5回戦】DeNA・牧の守備…","昨日のT・周平の守備ｗｗｗｗｗｗ"]},{"rank":11,"word":"先制","search_keys":["先制"],"count":5,"sample_titles":["【巨人対中日5回戦】巨人、2回裏1アウト一三塁から佐々木俊輔のタイムリーで先制！！！！！！！！！","栗原陵矢の先制ソロホームラン！！めっちゃ伸びるｗｗｗｗ","【西武対ソフトバンク5回戦】ソフトバンク・栗原、西武・高橋光成から第4号先制ソロホームラン！！！！！！！！！！！！"]},{"rank":12,"word":"大谷翔平","search_keys":["大谷翔平"],"count":5,"sample_titles":["【悲報】大谷翔平の二刀流ルールにカブス監督が批判ｗｗｗｗｗｗｗｗ","大谷翔平の一番の恩師 ←想像した人物wwwwwwwww","大谷翔平(32) .271(85-23) 5本 11打点 1盗塁 得点圏.158 OPS.890←率直な感想"]},{"rank":13,"word":"W杯","search_keys":["W杯"],"count":5,"sample_titles":["【サッカー】森保監督、W杯のメンバー選考「悩ましいですね」　怪我人のタイムリミットは「5月の初旬」","サウジ代表に激震！ルナール監督が電撃解任　直近2連敗…W杯まで2か月で急転直下の決断","【悲報】「日本はW杯に出ないほうがいい」発言で炎上の韓国代表レジェンド、「日本を見習うのが恥ずかしいのか」←これｗｗｗｗｗｗ"]},{"rank":14,"word":"ホークス","search_keys":["ホークス"],"count":5,"sample_titles":["ライオンズ対ホークス 18:00～（ベルーナドーム)","ホークス渡邉陸が今季初昇格","「緊張はしなかった」ホークス大竹風雅、2回無安打無失点と堂々プロデビュー"]},{"rank":15,"word":"久保建英","search_keys":["久保建英"],"count":4,"sample_titles":["【海外の反応】久保建英、10万人の優勝パレードで熱烈な「残留コール」を浴びる！","【サッカー】久保建英がプロ初タイトル！レアル・ソシエダ、アトレティコをPK戦の末に下して2021年以来3回目の国王杯優勝を果たす","【悲報】久保建英さん…好きな漫画をワンピースと答えネットで叩かれるｗｗｗｗｗ"]}],"anige":[{"rank":1,"word":"ポケモン","search_keys":["ポケモン"],"count":10,"sample_titles":["イッシュ地方ってドット絵→3D化にとことん失敗してるポケモン多くね？","【ポケモンGO】新年早々神社でポケモンgoするのって罰当たりかな","【狂気】ポケモン1025匹の名前を歌う曲、制作決定！歌うのはあの方！"]},{"rank":2,"word":"ガンダム","search_keys":["ガンダム"],"count":7,"sample_titles":["【速報】Netflixガンダム実写映画、制作開始wwwww","【悲報】実写ガンダム(Netflix)のキャストwwwwwwwwwwwwwwwwwwww","【映画】「ガンダム」シリーズ初の実写映画、製作開始　ネットフリックス発表"]},{"rank":3,"word":"プラグマタ","search_keys":["プラグマタ"],"count":5,"sample_titles":["例のバイヤー「PS5本体の売れ行きが鈍すぎる。プラグマタではやはり本体牽引できない」","新作ゲー「プラグマタ」のディアナ、リアル幼女感がすごい・・・","PS5 PRO版プラグマタ　864P、Switch2の540Pに倍近い差を見せる"]},{"rank":4,"word":"スプラトゥーン","search_keys":["スプラトゥーン"],"count":5,"sample_titles":["【速報】スイッチ2ソフト『スプラトゥーン レイダース』2026年7月23日に発売決定！！","【速報】「スプラトゥーン レイダース」の発売日が7月23日に決定！すりみ連合の新しいamiiboも登場！！","スプラトゥーンレイダースってどういうゲーム？"]},{"rank":5,"word":"コナン","search_keys":["コナン"],"count":4,"sample_titles":["【驚愕】名作『名探偵コナン』凄い事に気付いたｗｗｗｗ「コナンの設定」って現実だと無理がありすぎるよな…もしかして…","コナンの映画で爆走していたアンテナ移動台車の「走行速度」、ヤバいｗｗｗｗｗｗｗ","昔のコナン「骨が溶ける…ぐあああああああ」 → 新一"]},{"rank":6,"word":"トモコレ","search_keys":["トモコレ"],"count":4,"sample_titles":["トモコレ、海外で前作の6.2倍の売上になる🥰","【速報】トモコレ、前作比520%増wwwww","トモコレ、訳がわからんほど売れる。Amazonで約8万販売🥺"]},{"rank":7,"word":"YouTuber","search_keys":["YouTuber"],"count":4,"sample_titles":["【画像】ゲーム批評系YouTuber「ナカイド」が顔出し解禁しイケメンと話題にwwwwwww","【画像】有名YouTuber、例の「ONICHA」に手を出した結果ｗｗｗ","【悲報】AI映画系YouTuber、収益化停止されてお気持ち表明ｗｗｗｗｗ"]},{"rank":8,"word":"ドラゴン","search_keys":["ドラゴン"],"count":4,"sample_titles":["【悲報】未来悟飯さん、ドラゴンボール史上最も悲惨な人生だったｗｗｗ","【衝撃】ドラゴンボールGT、主題歌と最終回のおかげで全部が許されるｗｗｗｗ","【驚愕】名作『ドラゴンボール』のイケメン認定キャラがこちらｗｗｗｗこのキャラは…"]},{"rank":9,"word":"ドラクエ","search_keys":["ドラクエ"],"count":3,"sample_titles":["【命題】ドラクエ4のメンバーってけっこう隙なしだよな","【画像】ドラクエ10、民度が落ちるとこまで落ちる","ドラクエ10安西D「サービスが空洞化する不安を感じる人が多くいるが、そうならないように全力を尽くしたい」"]},{"rank":10,"word":"末路","search_keys":["末路"],"count":3,"sample_titles":["【衝撃】未開封のまま約30年保管されたツアーTシャツの末路ｗｗｗｗｗｗ","【驚愕】最近の女子大生がヤバすぎるｗｗｗｗ31歳でイケメンのワイ、バイト先の女子大生に凄い事を言われてしまう…ワイの末路が…","【衝撃】ワイ、大学に7年通うも必要単位が取れず無事除籍になるｗｗｗｗワイの末路が…悲惨すぎる…"]},{"rank":11,"word":"Vtuber","search_keys":["Vtuber"],"count":3,"sample_titles":["Vtuber事務所「所属の男性Vと女性Vが◯◯したため、ルール違反で契約解除しました」←とんでもないこと暴露してるんだが","【衝撃】「Vtuber」がオタク界隈の覇権を握った理由ｗｗｗｗもしかして…最近のオタクは…","【速報】人気Vtuber、社内恋愛違反で契約解除ｗｗｗｗｗｗｗｗｗ"]},{"rank":12,"word":"違反","search_keys":["違反"],"count":3,"sample_titles":["Vtuber事務所「所属の男性Vと女性Vが◯◯したため、ルール違反で契約解除しました」←とんでもないこと暴露してるんだが","【速報】人気Vtuber、社内恋愛違反で契約解除ｗｗｗｗｗｗｗｗｗ","【衝撃】最近の絵本、レギュレーション違反が見つかるｗｗｗｗｗｗｗｗ"]},{"rank":13,"word":"契約解除","search_keys":["契約解除"],"count":3,"sample_titles":["Vtuber事務所「所属の男性Vと女性Vが◯◯したため、ルール違反で契約解除しました」←とんでもないこと暴露してるんだが","【速報】人気Vtuber、社内恋愛違反で契約解除ｗｗｗｗｗｗｗｗｗ","【悲報】VTuber、事務所内恋愛がバレて契約解除になるｗｗｗｗ"]},{"rank":14,"word":"ジャンプ","search_keys":["ジャンプ"],"count":3,"sample_titles":["【朗報】ジャンプ＋で読切が好評だった「ヒトナー」、新連載開始！！2話目も面白くて期待出来そうｗｗｗｗ","チェンソーマンの終わり方にブチギレてる。ジャンプに苦情入れてえ","「幕張」とかいうジャンプで連載してたギャグ漫画ｗｗｗｗｗｗｗｗｗｗｗｗｗｗｗｗｗｗｗｗｗｗ"]},{"rank":15,"word":"導入","search_keys":["導入"],"count":3,"sample_titles":["【朗報】ニコニコ動画、『AI盛り上げ隊』を導入して過疎化対策を図る","【画像】ヒカキンの麦茶「オニチャ」、売れ過ぎて購入制限導入wwwwwww","京楽「e ライザのアトリエ ～常闇の女王と秘密の隠れ家～」公式PV公開！　全国導入は5月7日"]}]},"popular":[{"rank":1,"word":"人間","search_keys":["人間"],"count":2,"sample_titles":["【海外の反応】「開けてー、帰ってきたよ」　ドアをノックして帰宅を告げる猫に海外大興奮「しつけられてるのは人間の方」","姪（7）「人間みんなネコさんになっちゃえば戦争もなくなるよ？」←"]},{"rank":2,"word":"ユダヤ","search_keys":["ユダヤ"],"count":2,"sample_titles":["ユダヤ大富豪ジョージ・ソロス氏が日本を標的に？極左政策（難民・LGBTQ）関連団体への巨額助成金が発覚[海外の反応]","イスラエル兵士が「キリスト像」をハンマーで破壊し世界中から批判殺到…ユダヤに根強く残る「反キリスト思想」を反映か？[海外の反応]"]},{"rank":3,"word":"攻略","search_keys":["攻略"],"count":2,"sample_titles":["昔のゲーム攻略本って覚えてる？","【悲報】クレーンゲームの有名確率機、YouTuberに座標ずらしという攻略をされ全国で使用停止が相次ぐ"]},{"rank":4,"word":"OG","search_keys":["OG"],"count":2,"sample_titles":["五百城茉央さん、アンダー先輩との写真はほとんど投稿しないのにOGの山下美月との写真は即投稿するあざとさを魅せる","【日向坂46】あのOGに近づいていくw 松尾桜『STAR WARS』仕事ｷﾀ━━(ﾟ∀ﾟ)━━!!"]},{"rank":5,"word":"秋元康","search_keys":["秋元康"],"count":2,"sample_titles":["【闇深】秋元康さん、自分のラジオのゲストにカワラボPの木村ミサを指名ｗｗｗｗｗｗｗｗｗｗｗ","秋元康さん「最近は坂道も選抜やセンターは...」「だからビリヤニという曲を作った」"]},{"rank":6,"word":"選抜","search_keys":["選抜"],"count":2,"sample_titles":["秋元康さん「最近は坂道も選抜やセンターは...」「だからビリヤニという曲を作った」","菅原副キャプテンは二人だけ選抜に放り込まれた6期生のフォローやケアを怠ってんの？廊下で飯食う羽目になってるけど菅原、お前何やってんの？"]}]}