{"schema_version":1,"updated_at":"2026-05-14T22:50:18.002601+00:00","hours_window":24,"categories":{"all":[{"rank":1,"word":"カルビー","search_keys":["カルビー"],"count":46,"sample_titles":["カルビー「ポテチ」など値上げへ","【悲報】転売ヤーさん、カルビーに目をつけるｗｗｗｗ （※画像あり）","カルビー「ポテトチップス」が白黒に…土田晃之「この宣伝効果はめちゃめちゃでかい」古市憲寿も「カルビー最高ですよね」"]},{"rank":2,"word":"ナフサ不足","search_keys":["ナフサ","ナフサ不足"],"count":38,"sample_titles":["マルタイ「棒ラーメン」を束ねる色付きテープが入手困難、ナフサ不足で…「生産が止まらないよう努力」","【悲報】日本企業さん、ナフサ不足でヒーヒー言い出す","マルタイ､ナフサ不足で棒ラーメンの麺を束ねる色付きテープが入手困難に"]},{"rank":3,"word":"白黒","search_keys":["白黒"],"count":26,"sample_titles":["落語家「白黒のままでもポテトは食えるが、高市総理にナフサは買えません」うまい！！よっ！","カルビー「ポテトチップス」が白黒に…土田晃之「この宣伝効果はめちゃめちゃでかい」古市憲寿も「カルビー最高ですよね」","【朗報】読売ジャイアンツ、全てが白黒になるブラックデー開催を発表！！！！"]},{"rank":4,"word":"大谷翔平","search_keys":["大谷","大谷翔平"],"count":25,"sample_titles":["【凄い】投手大谷翔平さん、安定感がレベチ過ぎてリーグ最強投手だと話題にｗｗｗｗ","【悲報】大谷翔平さん、サイヤング候補で1人だけおっさんだった","【朗報】大谷翔平さん、7試合連続QS達成で防御率メジャーリーグ全体1位独走ｗｗｗｗｗ"]},{"rank":5,"word":"辺野古転覆","search_keys":["辺野古","辺野古転覆"],"count":21,"sample_titles":["ABCテレビ『newsおかえり』内で辺野古転覆を40分に渡り徹底特集し追求","抗議団体関係者から「2人死んじゃった」と笑いながら声をかけられた／「海人の証言は噓」辺野古転覆、抗議団体の発言を漁業者が否定　事故当日「うねりすごく」","辺野古転覆 漁協支部長が真実語る 抗議団体関係者に「二人死んじゃった」笑いながら話しかけられる"]},{"rank":6,"word":"NHK高校講座","search_keys":["NHK","NHK高校講座"],"count":20,"sample_titles":["【超画像】NHK高校講座地学の生徒役(27)、現役高校生に刺激が強すぎる…","【画像】NHK高校講座地学の生徒役(27)、現役高校生に刺激が強すぎる…","【画像】NHK高校講座地学の生徒役(27)の身体、現役高校生には刺激が強すぎる…"]},{"rank":7,"word":"ポケモンカード","search_keys":["ポケモン","ポケモンカード"],"count":19,"sample_titles":["【動画】アメリカ大手メディア「ポケモンカードは今や本格的な価値を持つ資産となった」","ブルバ「ポケモンカードは今や本格的な価値を持つ資産となった」","ブルームバーグ「ポケモンカードは今や本格的な価値を持つ資産となった」"]},{"rank":8,"word":"トランプ訪中","search_keys":["トランプ","トランプ訪中"],"count":19,"sample_titles":["【画像】トランプ訪中、どっちが招待客か分からなくなる","トランプ訪中、どっちが招待客か分からなくなる   #画像 |  台湾有事発言から決まってたんだよ","【画像】トランプ訪中、どっちが招待客か分からなくなる"]},{"rank":9,"word":"防御率","search_keys":["防御率"],"count":18,"sample_titles":["【朗報】大谷翔平さん、7試合連続QS達成で防御率メジャーリーグ全体1位独走ｗｗｗｗｗ","大谷翔平 3勝2敗 防御率0.82 44回 奪三振50 WHIP0.82","海外「野球の神」大谷翔平の防御率がド軍史上に残るレベルまで低下したことに海外大騒ぎ！（海外の反応）"]},{"rank":10,"word":"カゴメ","search_keys":["カゴメ"],"count":16,"sample_titles":["【悲報】カゴメさん、インク不足でケチャップの袋を透明にしてしまう","カゴメ、ケチャップの袋から「トマト」が消える","【悲報】カゴメ、インク不足でケチャップの袋を透明に"]},{"rank":11,"word":"Switch","search_keys":["ch","Switch"],"count":16,"sample_titles":["【悲報】Switch2「グラブル」新作の女キャラさん、エッチすぎるｗｗｗｗｗｗｗｗｗｗ","任ファン「PS5の神ゲーをSwitch2でやりたい」←いやPS5買えよｗ","【画像】Switch2で7月発売「グラブルエンドレスラグナロク」の女キャラが可愛い"]},{"rank":12,"word":"アメリカ","search_keys":["アメリカ"],"count":16,"sample_titles":["【画像】アメリカのメスガキ、ガチでヤバすぎるｗｗｗｗｗｗｗｗｗｗｗｗｗｗｗｗ","打率なんてアメリカは誰も気にしてない←これまじ？　村上打率228","【悲報】アメリカで寿司ガキが社会問題に"]},{"rank":13,"word":"強盗殺人容疑","search_keys":["強盗","強盗殺人容疑"],"count":15,"sample_titles":["【悲報】16歳高校生君、バイト代0円で強盗殺人容疑で逮捕","【悲報】16歳高校生君、バイト代0円で強盗殺人容疑で逮捕","模原市の16歳高校生、強盗殺人容疑で逮捕　闇バイトか"]},{"rank":14,"word":"依頼","search_keys":["依頼"],"count":15,"sample_titles":["「会社辞めたい」GW明けの退職代行依頼が約3倍　SNSで加速する早期退職...“ホワイトすぎて辞める”新入社員も","【悲報】コスプレイヤーさん、5万円で依頼した小道具の出来栄えがひどすぎて泣く","【衝撃】コスプレイヤーさん、5万円で依頼した小道具の出来栄えが酷すぎた結果ｗｗｗｗｗ(※画像あり)"]},{"rank":15,"word":"変更","search_keys":["変更"],"count":15,"sample_titles":["カゴメ､インク不足で｢ケチャップ｣のパッケージを変更 トマトを減らして透明に","【ナフサ】ごみ袋の買いだめ控えて　ナフサ不足懸念　素材変更決めた市も","【ナフサショック】カゴメ、トマトケチャップの外袋を透明に変更！中東情勢で白インクが足りない！"]}],"news":[{"rank":1,"word":"カルビー","search_keys":["カルビー"],"count":20,"sample_titles":["カルビー ポテトチップス 値上げ","【速報】カルビー、中東影響30億円損失を盛り込んでも今期純利益0.4％「最​大１０％程度値上げ発表」","原油「そろそろ節約すべき時」専門家が指摘「足りている」政府主張と企業側に認識のズレ ナフサ不足で広がる影響 景気に深刻影響   |  相変わらずカルビーの件が引き合いに出されてんな"]},{"rank":2,"word":"ナフサ不足","search_keys":["ナフサ","ナフサ不足"],"count":19,"sample_titles":["マルタイ､ナフサ不足で棒ラーメンの麺を束ねる色付きテープが入手困難に","シンナー棚が空っぽ…“イラン情勢”でナフサ不足深刻化　エンジンオイルも品薄へ","原油「そろそろ節約すべき時」専門家が指摘「足りている」政府主張と企業側に認識のズレ ナフサ不足で広がる影響 景気に深刻影響   |  相変わらずカルビーの件が引き合いに出されてんな"]},{"rank":3,"word":"辺野古","search_keys":["辺野古"],"count":18,"sample_titles":["【波紋】参政・梅村氏「辺野古より南丹の報道多くない？」→NHK副会長「逮捕まで3週間かかったため」と説明","関西ABCテレビ、地上波で渾身の辺野古特集「あまりに異質な事故」   |  済んだことをいつまでもグジャグジャうるせえ  |  キー局はもうダメだわ","【磐越道バス事故】生徒「シートベルトしよう」運転に危険感じグループLINEで共有　辺野古もたけど生徒はまともなんだよなぁ"]},{"rank":4,"word":"白黒","search_keys":["白黒"],"count":13,"sample_titles":["落語家「白黒のままでもポテトは食えるが、高市総理にナフサは買えません」うまい！！よっ！","【高市悲報】カルビーに続き、「伊藤ハム」も白黒包装へ","企業「ナフサ不足でヤバい」国民「ふーん」カルビー「ナフサ不足で白黒印刷しかできん」国民「！」"]},{"rank":5,"word":"高市首相","search_keys":["高市","高市首相"],"count":12,"sample_titles":["高市首相は「媚びるのが下手」　「クネクネダンス」や「不自然な笑顔」の女性が「この国の顔」になった意味　北原みのり氏","高市首相「研究費倍増目指す」技術立国に向け…大学認定制度も！","「嘘つき政治家人生」のルーツを発掘！ 34年前に自ら堂々と「経歴詐称」を認めていた   #高市首相 |  こんなスレ立ててタダですむと思うなよ"]},{"rank":6,"word":"トランプ訪中","search_keys":["トランプ","トランプ訪中"],"count":12,"sample_titles":["【画像】トランプ訪中、どっちが招待客か分からなくなる","トランプ訪中、どっちが招待客か分からなくなる   #画像 |  台湾有事発言から決まってたんだよ","【画像】トランプ訪中、どっちが招待客か分からなくなる"]},{"rank":7,"word":"NHK","search_keys":["NHK"],"count":11,"sample_titles":["【波紋】参政・梅村氏「辺野古より南丹の報道多くない？」→NHK副会長「逮捕まで3週間かかったため」と説明","【速報】参政党・梅村氏「平和丸船長の名前が出ないのはなぜ？」 NHK「関係者の事情等を考慮して...」","NHK 「辺野古事故の報道が少ないのは、こちらの判断。何を報道するかはこっちが決める」"]},{"rank":8,"word":"強盗殺人容疑","search_keys":["強盗","強盗殺人容疑"],"count":10,"sample_titles":["【悲報】16歳高校生君、バイト代0円で強盗殺人容疑で逮捕","【悲報】16歳高校生君、バイト代0円で強盗殺人容疑で逮捕","模原市の16歳高校生、強盗殺人容疑で逮捕　闇バイトか"]},{"rank":9,"word":"変更","search_keys":["変更"],"count":10,"sample_titles":["カゴメ､インク不足で｢ケチャップ｣のパッケージを変更 トマトを減らして透明に","【ナフサ】ごみ袋の買いだめ控えて　ナフサ不足懸念　素材変更決めた市も","【ナフサショック】カゴメ、トマトケチャップの外袋を透明に変更！中東情勢で白インクが足りない！"]},{"rank":10,"word":"大谷翔平","search_keys":["大谷翔平"],"count":10,"sample_titles":["海外「野球の神」大谷翔平の防御率がド軍史上に残るレベルまで低下したことに海外大騒ぎ！（海外の反応）","大谷翔平、7回0封8Kで今季3勝目！防御率0.82でメジャートップ浮上","「大谷翔平はもはや最高の日本人選手ではない」「村上宗隆が功績を横取り」米国で衝撃報道   #MLB"]},{"rank":11,"word":"自民","search_keys":["自民"],"count":9,"sample_titles":["高市自民も震撼！ 韓国では旧統一教会が“丸裸”に…マザームーンこと韓鶴子被告の横領疑惑に強制捜査のメス   |  韓国人発祥のパチンコも違法になってるんだっけ","高市自民も震撼！ 韓国では旧統一教会が“丸裸”に…マザームーンこと韓鶴子被告の横領疑惑に強制捜査のメス","高市自民も震撼！ 韓国では旧統一教会が“丸裸”に…マザームーンこと韓鶴子被告の横領疑惑に強制捜査のメス"]},{"rank":12,"word":"少年","search_keys":["少年"],"count":9,"sample_titles":["逮捕された16歳少年は自称・神奈川県相模原市の高校生か 上三川町で住宅に侵入し69歳女性を殺害した疑い 栃木県警","逮捕された16歳少年は自称・神奈川県相模原市の高校生か　上三川町で住宅に侵入し69歳女性を殺害した疑い　栃木県警","【闇バイト】栃木の強盗傷害事件　複数人が押し入りバールで殴り69歳女性死亡　16歳少年確保に衝撃走る"]},{"rank":13,"word":"侵入","search_keys":["侵入"],"count":9,"sample_titles":["逮捕された16歳少年は自称・神奈川県相模原市の高校生か 上三川町で住宅に侵入し69歳女性を殺害した疑い 栃木県警","逮捕された16歳少年は自称・神奈川県相模原市の高校生か　上三川町で住宅に侵入し69歳女性を殺害した疑い　栃木県警","世田谷一家殺害の現場に侵入容疑、ベトナム人2人逮捕　金品狙ったか"]},{"rank":14,"word":"栃木県警","search_keys":["栃木","栃木県警"],"count":9,"sample_titles":["逮捕された16歳少年は自称・神奈川県相模原市の高校生か 上三川町で住宅に侵入し69歳女性を殺害した疑い 栃木県警","逮捕された16歳少年は自称・神奈川県相模原市の高校生か　上三川町で住宅に侵入し69歳女性を殺害した疑い　栃木県警","栃木・上三川町の事件で16歳少年を強盗殺人容疑で逮捕 栃木県警   |  16歳だから死刑は免れたな"]},{"rank":15,"word":"確保","search_keys":["確保"],"count":9,"sample_titles":["【闇バイト】栃木の強盗傷害事件　複数人が押し入りバールで殴り69歳女性死亡　16歳少年確保に衝撃走る","【速報】日本、エネルギー確保へ","「バールで殴られた」栃木の強盗傷害事件…69歳女性死亡　16歳少年確保"]}],"entame":[{"rank":1,"word":"ぱい","search_keys":["ぱい"],"count":6,"sample_titles":["【画像】二瓶有加さんお◯ぱいが過ぎるwwwwwwwwwwwwwwwwwwwwwwwwwww【ニヘラチオ】","令和のお◯ぱいバレー、見つかるwwwwwwww（動画あり）","【画像】全盛期・生田絵梨花のお●ぱいがレベチ！！！"]},{"rank":2,"word":"お披露目","search_keys":["お披露目"],"count":4,"sample_titles":["【すぺしゃりて】本阿弥あずさ新衣装お披露目！ボタンが苦しそう","【にじさんじ】力一島の戌亥、お披露目でしゃっくりしてるし歯に惚れてて草","【RIOTMUSIC】朕3Dお披露目！白朕黒朕初オリ曲うおおおおおおお"]},{"rank":3,"word":"身体","search_keys":["身体"],"count":3,"sample_titles":["【画像】あのちゃんの身体のエ□さが限界突破！これはもう抜けるレベル！","【画像】全盛期・沢口愛華の身体がガチでエ□すぎる！これもう全身性器じゃね？","【画像】NHK高校講座地学の生徒役(27)の身体、現役高校生には刺激が強すぎる…"]},{"rank":4,"word":"楽曲","search_keys":["楽曲"],"count":3,"sample_titles":["【日向坂46】ひなた坂46楽曲『Empty』のMVを視聴したおひさまの率直な感想がこちら…","【ひなた坂46】17thひらがな楽曲『Empty』MV＆音源 初解禁！おひさまの反応がこちら","【VTuber】CIELの5周年記念楽曲『君と旅風』MVが美しすぎる…"]},{"rank":5,"word":"収録","search_keys":["収録"],"count":3,"sample_titles":["【にじさんじ】みくぽぽ、5月15日からのラジオは3日間事前収録回","【にじさんじ】みくぽぽ「今日からラジオは3日間事前収録回となります」← 今日からホテルに拘束されるライバー結構多そうやな","【ホロライブ】こより、休暇4日目「収録行ってくるよー！！！( ͒ •·̫• ͒)✨」"]},{"rank":6,"word":"衣装","search_keys":["衣装"],"count":3,"sample_titles":["【すぺしゃりて】本阿弥あずさ新衣装お披露目！ボタンが苦しそう","【ホロライブ】アキ・ローゼンタール、ついに広告衣装実装🍎本日19時スタート！","【すぺしゃりて】あじゅ姉新衣装、実況感想まとめ『でっか』『ボタンが苦しそう』『ハンカチ噛んで悔しがる17歳』"]}],"neta":[{"rank":1,"word":"カルビー","search_keys":["カルビー"],"count":20,"sample_titles":["カルビー「ポテチ」など値上げへ","【悲報】転売ヤーさん、カルビーに目をつけるｗｗｗｗ （※画像あり）","カルビー「ポテトチップス」が白黒に…土田晃之「この宣伝効果はめちゃめちゃでかい」古市憲寿も「カルビー最高ですよね」"]},{"rank":2,"word":"ナフサ","search_keys":["ナフサ"],"count":18,"sample_titles":["【悲報】日本企業さん、ナフサ不足でヒーヒー言い出す","【経済】川崎重工、水素からナフサを生産する技術を提案　原油の代わりに","【悲報】ナフサは足りてるのにパッケージを変えなきゃいけない理由がガチでヤバすぎるｗｗｗｗｗｗｗｗｗｗ"]},{"rank":3,"word":"芸人","search_keys":["芸人"],"count":11,"sample_titles":["【朗報】中山功太さん、ダサい芸人を暴露する","【悲報】お笑い芸人さん「4月～6月生まれの女は避けろ。親が夏に盛って産んだ子」ｗｗｗｗｗｗｗｗｗｗ","【悲報】お笑い芸人さん「4月～6月生まれの女は避けろ。親が夏に盛って生まれた子。親がバカだから」"]},{"rank":4,"word":"サバンナ高橋さん","search_keys":["サバンナ高橋","サバンナ高橋さん"],"count":10,"sample_titles":["【悲報】サバンナ高橋さん、15年務めた『ストッパ下痢止め』のCMをガチで降板させられてしまうｗｗｗｗｗｗｗｗｗｗ","【悲報】サバンナ高橋さん、15年務めたストッパ下痢止めの公式サイトから写真を消されてしまう","【悲報】ライオンさん「サバンナ高橋さんをCMから降板させます」"]},{"rank":5,"word":"提案","search_keys":["提案"],"count":9,"sample_titles":["【日テレ】宮根誠司　消費税減税の議論で「ぜいたく税」を提案し「困る？僕はぜいたくしない。コンビニで十分」","韓国・李大統領　ベッセント財務長官に通貨スワップ締結を提案　米側は特に扱わず","【緊迫】ロシア、日本政府に『とんでもない提案』をしてしまう！！！！！！"]},{"rank":6,"word":"白黒","search_keys":["白黒"],"count":9,"sample_titles":["カルビー「ポテトチップス」が白黒に…土田晃之「この宣伝効果はめちゃめちゃでかい」古市憲寿も「カルビー最高ですよね」","【悲報】カルビーに続き、「伊藤ハム」も白黒包装へ","【悲報】カルビーさん、ナフサ節約のためにパッケージを白黒にしたら政府に呼び出されてしまうｗｗｗｗｗｗｗｗｗｗ"]},{"rank":7,"word":"カゴメ","search_keys":["カゴメ"],"count":8,"sample_titles":["【悲報】カゴメさん、インク不足でケチャップの袋を透明にしてしまう","【悲報】カゴメ、インク不足でケチャップの袋を透明に","【大悲報】カゴメ、インク不足でケチャップの袋を透明に・・・・・"]},{"rank":8,"word":"CM","search_keys":["CM"],"count":8,"sample_titles":["【悲報】マックCMのアイドルさん、バーガー食べたフリがバレて翌日に完食動画を出されてしまうｗｗｗｗｗｗｗｗｗｗ","【悲報】サバンナ高橋さん、15年務めた『ストッパ下痢止め』のCMをガチで降板させられてしまうｗｗｗｗｗｗｗｗｗｗ","【悲報】マクドナルドさん、CMでアイドルにハンバーガーを食べたフリさせてしまう"]},{"rank":9,"word":"日産","search_keys":["日産"],"count":8,"sample_titles":["日産追浜工場「九州に引っ越すか、いすゞに転職するか、どっちが良い？」","【訃報】日産、約533,000,000,000円の赤字ｗｗｗｗｗｗｗｗｗｗｗｗｗｗｗｗｗｗ","日産追浜工場「九州に引っ越すか、いすゞに転職するか、どっちが良い？」"]},{"rank":10,"word":"依頼","search_keys":["依頼"],"count":8,"sample_titles":["「会社辞めたい」GW明けの退職代行依頼が約3倍　SNSで加速する早期退職...“ホワイトすぎて辞める”新入社員も","【悲報】コスプレイヤーさん、5万円で依頼した小道具の出来栄えがひどすぎて泣く","【衝撃】コスプレイヤーさん、5万円で依頼した小道具の出来栄えが酷すぎた結果ｗｗｗｗｗ(※画像あり)"]},{"rank":11,"word":"トランプ","search_keys":["トランプ"],"count":8,"sample_titles":["トランプ氏、イラン問題で中国の支援｢不要｣　打開策｢飛行機で考える｣","【国際】ロシア・ウクライナ、9日から3日間停戦　トランプ氏「私が要請」","【悲報】トランプさん、アメリカ人達に『暴言』を吐いてしまう！！！！！"]},{"rank":12,"word":"アメリカ","search_keys":["アメリカ"],"count":8,"sample_titles":["【画像】アメリカのメスガキ、ガチでヤバすぎるｗｗｗｗｗｗｗｗｗｗｗｗｗｗｗｗ","【悲報】アメリカで寿司ガキが社会問題に","【動画】アメリカ大手メディア「ポケモンカードは今や本格的な価値を持つ資産となった」"]},{"rank":13,"word":"W杯","search_keys":["W杯"],"count":7,"sample_titles":["【悲報】サッカーW杯さん、「たぶん観ない」が48.7％でガチのマニア向けコンテンツになってしまうｗｗｗｗｗｗｗｗｗｗ","【朗報】三笘さん、W杯に間に合わない訳では無い模様ｗｗｗｗｗｗｗｗｗｗ","【悲報】W杯決勝さん、史上初のハーフタイムショーを実施してしまうｗｗｗｗｗｗｗｗｗｗ"]},{"rank":14,"word":"Switch","search_keys":["Switch"],"count":7,"sample_titles":["【悲報】Switch2「グラブル」新作の女キャラさん、エッチすぎるｗｗｗｗｗｗｗｗｗｗ","【画像】Switch2で7月発売「グラブルエンドレスラグナロク」の女キャラが可愛い","【悲報】Switch2さん、買ったはいいけどガチでやるカセットがない・・・・・・・・・"]},{"rank":15,"word":"YouTuber","search_keys":["YouTuber"],"count":7,"sample_titles":["子どもに安心して見せられるYouTuber","【悲報】ヒカルさん「一部の人に強烈にブッ刺さる人であり続けたい」「俺は日本一のYouTuberになる」","登録者200万人超えYouTuber、Xの収益を赤裸々告白　“リアル”な金額にネット「これは夢のある話」「クリエイターってすごい」"]}],"life":[{"rank":1,"word":"ベルコ","search_keys":["ベルコ"],"count":4,"sample_titles":["【新台】ベルコ「Lすーぱぁびん娘」簡易スペックが公開！ATは下位・上位ともに1セット100G！","ベルコが「エニィバー」を商標出願！","【新台】ベルコ「Lすーぱぁびん娘」スクープ映像が公開！"]},{"rank":2,"word":"試打","search_keys":["試打"],"count":3,"sample_titles":["【新台】オーイズミ「L喰霊-零-Re」ショート試打動画が公開！","【新台】ダイイチ「P犬夜叉3.0 大入り甘SPEC」試打動画が公開！","【新台】SANKYO「Lパチスロからくりサーカス2」新たな実機画像&試打の感想が公開される！内蔵のデータ表示機能めっちゃ便利そう"]},{"rank":3,"word":"中東情勢","search_keys":["中東情勢"],"count":3,"sample_titles":["「いよいよマズイかな」 緊迫する中東情勢 店頭から消えたナフサ由来商品 シンナーやエンジンオイルの棚は殆ど“空” 政府と現場に生じる“ズレ”","カルビーが「ポテトチップス」「じゃがりこ」の一部を値上げへ…中東情勢の影響ではないと説明","指定ごみ袋「買いだめ自粛」呼びかけ、「代替ごみ袋」認める措置も…中東情勢への不安で「ほぼ完売」相次ぎ"]},{"rank":4,"word":"下着","search_keys":["下着"],"count":3,"sample_titles":["【画像】菊地姫奈さん(21)、痩せて綺麗になったエッチ下着姿を披露してしまうｗｗｗｗｗ","【画像】菊地姫奈さん(21)、痩せて綺麗な下着姿wwwwwwwww","元NHKアナ・中川安奈が訴え「下着の線が見えてる」切り抜き写真がSNSに載せられることが多い"]},{"rank":5,"word":"実戦","search_keys":["実戦"],"count":3,"sample_titles":["【新台】藤商事「eひきこまり吸血姫の悶々」5ch実戦感想＆評価まとめ！「CZいらない」「CZ中の金色はずれる」「RUSH面白くない」等","【新台】京楽「eライザのアトリエ 常闇の女王と秘密の隠れ家」5ch実戦感想＆評価まとめ！「究極連鎖BONUSの脳汁がすごい」「ゲームの演出がふんだんに使われてるのが良い」等","【新台】三共「PフィーバークィーンⅡ」実戦感想＆評価まとめ！「演出のメリハリがグッド」「大当たり消化が爆速でびっくりする」等"]},{"rank":6,"word":"パチスロ","search_keys":["パチスロ"],"count":3,"sample_titles":["3大好印象なパチスロ5号機「鉄拳デビル」「初代忍魂」「ハードボイルド」","【朗報】SANKYO「FORTUNE枠レバーラバーボールチェーン」&「パチスロからくりサーカス メタルキーホルダー」が爆誕","【新台】SANKYO「Lパチスロからくりサーカス2」新たな実機画像&試打の感想が公開される！内蔵のデータ表示機能めっちゃ便利そう"]},{"rank":7,"word":"びん","search_keys":["びん"],"count":3,"sample_titles":["【新台】ベルコ「Lすーぱぁびん娘」簡易スペックが公開！ATは下位・上位ともに1セット100G！","【新台】ベルコ「Lすーぱぁびん娘」スクープ映像が公開！","【噂】ベルコ「Lすーぱぁびん娘」導入日は8月3日予定！？"]},{"rank":8,"word":"うどん","search_keys":["うどん"],"count":3,"sample_titles":["１００%美味いであろううどんのスープ作ってる","【朗報】ハシカン、うどんにハマる","【悲報】はなまるうどん、かつやイズムを手に入れる"]},{"rank":9,"word":"セブン","search_keys":["セブン"],"count":3,"sample_titles":["【悲報】セブンの大増量二郎系ラーメン食った感想、ヤバすぎる","セブンのカップラーメンで一番美味いものといえば？","【悲報】セブンの大増量二郎系ラーメン食った感想、ヤバすぎる"]}],"sports":[{"rank":1,"word":"大谷翔平","search_keys":["大谷翔平"],"count":13,"sample_titles":["【悲報】大谷翔平さん、サイヤング候補で1人だけおっさんだった","【朗報】大谷翔平さん、7試合連続QS達成で防御率メジャーリーグ全体1位独走ｗｗｗｗｗ","大谷翔平 3勝2敗 防御率0.82 44回 奪三振50 WHIP0.82"]},{"rank":2,"word":"防御率","search_keys":["防御率"],"count":13,"sample_titles":["【朗報】大谷翔平さん、7試合連続QS達成で防御率メジャーリーグ全体1位独走ｗｗｗｗｗ","大谷翔平 3勝2敗 防御率0.82 44回 奪三振50 WHIP0.82","大谷翔平、7試合連続QS達成で防御率メジャー全体1位独走ｗｗｗｗｗｗ"]},{"rank":3,"word":"中日ドラゴンズ","search_keys":["中日","中日ドラゴンズ"],"count":10,"sample_titles":["中日ドラゴンズ、打率上位の打者５人を起用せず・・","中日ドラゴンズ、何故か細川の前で送りバントをしてしまい案の定細川が敬遠されてしまうｗｗｗｗｗｗｗｗｗｗｗｗｗｗｗｗｗｗｗ","【実況・雑談用】5/14公式戦　横浜DeNAベイスターズvs中日ドラゴンズ"]},{"rank":4,"word":"ロッテ","search_keys":["ロッテ"],"count":10,"sample_titles":["ロッテ、お立ち台４人","5月14日　ロッテ５－３日本ハム　先発西野が9回途中2失点の好投で今季初勝利！佐藤の一発など初回先制し無事逃げ切り連敗ストップ！","【ロッテ対日本ハム9回戦】ロッテ・西川史礁、日本ハム・細野から第２号ソロホームラン！リードを３点に広げる！！！！！！！！！！！！！！"]},{"rank":5,"word":"W杯","search_keys":["W杯"],"count":9,"sample_titles":["【悲報】ブライトン監督「非常に大きな痛手だ」三笘のW杯出場は不透明に。イングランド現地「無理してキャリアを壊さないで」","【悲報】日本代表、W杯直前に野戦病院化で米メディアから「3バックは諦めろ」と宣告される…。","【速報】フジテレビ、W杯で放送する10カードを発表ｗｗｗｗｗｗｗ"]},{"rank":6,"word":"日本ハム","search_keys":["日本ハム"],"count":7,"sample_titles":["5月14日　ロッテ５－３日本ハム　先発西野が9回途中2失点の好投で今季初勝利！佐藤の一発など初回先制し無事逃げ切り連敗ストップ！","日本ハム連勝ストップ...9回浅間清宮連続アーチで猛追も及ばず、細野6回途中4失点降板","【ロッテ対日本ハム9回戦】日本ハム・清宮、ライトポール直撃の第8号ソロホームラン！！！！！！！！！！！！！"]},{"rank":7,"word":"井上一樹","search_keys":["井上","井上一樹"],"count":6,"sample_titles":["Q.井上一樹監督が昨日12回の激闘で余らせた選手の数は？(ヒント:横浜は5人)","【朗報】井上一樹「今日はよく頑張った」","【朗報】中日井上一樹「同じ失敗を何回もしてるようではダメでしょ」「もっと考えなさい」「生ぬるくやっていたら、もちろんしかるよ」"]},{"rank":8,"word":"細野","search_keys":["細野"],"count":5,"sample_titles":["日本ハム連勝ストップ...9回浅間清宮連続アーチで猛追も及ばず、細野6回途中4失点降板","【ロッテ対日本ハム9回戦】ロッテ・西川史礁、日本ハム・細野から第２号ソロホームラン！リードを３点に広げる！！！！！！！！！！！！！！","【ロッテ対日本ハム9回戦】ロッテ・佐藤都志也、日本ハム・細野から第5号2ランホームラン！！！！！！！！！！！！！！！！！"]},{"rank":9,"word":"ドジャース","search_keys":["ドジャース"],"count":5,"sample_titles":["【朗報】ドジャース編成本部長「佐々木朗希はマイナーには落とさない。最高峰の打者と戦う事が成長につながる」","【朗報】ドジャースGM「佐々木朗希はマイナーには落とさない。最高峰の打者と戦う事が成長につながる」","大谷翔平に援護点！ドジャースが3回裏にエスピナルとベッツの二者連続ホームランで先制！！！！！！！！！！！！！！"]},{"rank":10,"word":"横浜","search_keys":["横浜"],"count":4,"sample_titles":["Q.井上一樹監督が昨日12回の激闘で余らせた選手の数は？(ヒント:横浜は5人)","横浜の印象は？　元SB井上朋也「赤レンガ倉庫とかある」","「横浜の印象は？」元SB井上「赤レンガ倉庫とかある」"]},{"rank":11,"word":"守田英正","search_keys":["守田英正"],"count":4,"sample_titles":["【朗報】外国人「あり得る」守田英正、レアル・マドリード移籍浮上！就任濃厚のモウリーニョ監督が獲得熱望!?海外のマドリディスタが騒然！【海外の反応】","守田英正、モウリーニョから過去2回コールあったのは確かなのか？","【速報】守田英正さん…まさかのレアルマドリー移籍かｗｗｗｗｗｗｗｗ"]},{"rank":12,"word":"レアル","search_keys":["レアル"],"count":4,"sample_titles":["【朗報】外国人「あり得る」守田英正、レアル・マドリード移籍浮上！就任濃厚のモウリーニョ監督が獲得熱望!?海外のマドリディスタが騒然！【海外の反応】","【悲報】レアル・マドリードさん、リーダー不在でOBから「キャプテン3人とも退団しろ」と死体蹴りされる…。","【速報】守田英正さん…まさかのレアルマドリー移籍かｗｗｗｗｗｗｗｗ"]},{"rank":13,"word":"坂本勇人","search_keys":["坂本勇人"],"count":4,"sample_titles":["坂本勇人がメジャー行かなかった理由","5/13 12回裏 坂本勇人サヨナラ3ラン　次の打者：松本剛","5/13 坂本勇人サヨナラ3ラン　次の打者：松本剛"]},{"rank":14,"word":"メジャー","search_keys":["メジャー"],"count":4,"sample_titles":["坂本勇人がメジャー行かなかった理由","大谷翔平、7試合連続QS達成で防御率メジャー全体1位独走ｗｗｗｗｗｗ","【朗報】大谷翔平さん、xERA（期待防御率）もメジャートップクラスであることが判明wwwwwwwwww"]},{"rank":15,"word":"ヤクルト","search_keys":["ヤクルト"],"count":4,"sample_titles":["【悲報】元ヤクルト助っ人に逮捕状","ヤクルトは落ちてくる！←落ちてこない　中日は上がってくる！←上がってこない","ヤクルト池山監督って有能なの？"]}],"anige":[{"rank":1,"word":"ポケモン","search_keys":["ポケモン"],"count":14,"sample_titles":["お前ら新作ポケモンWWの御三家どれ選ぶがそろそろ決めたのかよ？","ポケモンチャンピオンズ「ポケモン追加は3ヶ月スパン」","能登の和倉温泉が、ポケモンとコラボ。復興への足がかりへ！"]},{"rank":2,"word":"Switch","search_keys":["Switch"],"count":6,"sample_titles":["任ファン「PS5の神ゲーをSwitch2でやりたい」←いやPS5買えよｗ","カプコン、Switch2でDL率100%達成www","バイオショッククリエイター「リアリズムはもう限界、ユーザーもSwitch2とps5のグラの差に気づけない」"]},{"rank":3,"word":"ホロライブ","search_keys":["ホロライブ"],"count":5,"sample_titles":["【速報】ホロライブ谷郷社長、タレントマネジメント復帰、原点回帰へ","ホロライブ社長・谷郷元昭氏、タレント部門責任者に就任　タレントマネジメントを直轄","ホロライブ、ガチでやばすぎることになる・・・『ホロアース』の失敗で損失◯◯円・・・"]},{"rank":4,"word":"ホロアース","search_keys":["ホロアース"],"count":5,"sample_titles":["【サ終】ホロアース、サービス終了のお知らせ","ホロライブ、ガチでやばすぎることになる・・・『ホロアース』の失敗で損失◯◯円・・・","カバー、メタバースプロジェクト「ホロアース」のサービス終了を発表"]},{"rank":5,"word":"PS","search_keys":["PS"],"count":5,"sample_titles":["任ファン「PS5の神ゲーをSwitch2でやりたい」←いやPS5買えよｗ","PS5版「夜廻と深夜廻」、ひっそりと配信開始！","一般人「PCもPS5もSwitch2も値上げされて高くなってしまった。この中から選ぶならやはり…」"]},{"rank":6,"word":"鬼滅の刃","search_keys":["鬼滅の刃"],"count":4,"sample_titles":["【討論】鬼滅の刃の無惨様はどうしたら炭治郎達に勝てたのか今一度考えようｗｗｗｗ","【悲報】鬼滅の刃の最終回、この展開ならガチで大絶賛されてたｗｗｗｗ","【衝撃】鬼滅の刃の炭治郎「煉獄さんは凄い！」←わかる 「煉獄さんは負けてない！」←これｗｗｗ"]},{"rank":7,"word":"ワンピース","search_keys":["ワンピース"],"count":4,"sample_titles":["【朗報】ワンピースのくいなの正体、とうとうガチで判明したかもしれないｗｗｗ","【悲報】ワンピース見つけた奴が海賊王という風潮、ぶっちゃけおかしいｗｗｗ","【朗報】ワンピースの白ひげ海賊団、たった一人の馬鹿にめちゃくちゃにされてしまうｗｗｗ"]},{"rank":8,"word":"チー","search_keys":["チー"],"count":4,"sample_titles":["【動画】チー午、突然ゲームが終了して絶望ｗｗｗ","【画像】クラスのチー牛が使ってたシャーペン、大体コレｗｗｗｗ","【悲報】チー牛のDM、あまりにも怖すぎて女の子ドン引きｗｗｗｗ"]},{"rank":9,"word":"ガンダム","search_keys":["ガンダム"],"count":3,"sample_titles":["※食事にあんまり興味無さそうなガンダムキャラを集めるスレ","【閃ハサ】上司にしたくないガンダムの指揮官筆頭だな","【速報】バンダイナムコ決算『ガンダム』売上2543億円ｗｗｗ"]},{"rank":10,"word":"キャラクター","search_keys":["キャラクター"],"count":3,"sample_titles":["【悲報】満田拓也さん、キャラクターの設定を忘れてしまうwwwwwwwwwwwwwwwwwwww","おじゃる丸で一番嫌いなキャラクター、完全一致する","【悲報】メジャーセカンドさん、キャラクターの設定が原作とアニメで食い違ってしまうwwwwwwwwwwwwwwwwwwww"]},{"rank":11,"word":"性行為","search_keys":["性行為"],"count":3,"sample_titles":["県立高校でエチチ漫画みたいな展開…　顧問を務める部活動の女子部員2人と性行為","【悲報】30代高校教諭、部活の女子生徒2人と性行為したのがバレて懲戒解雇　関係を持っていた期間と回数がヤバすぎる・・・・","【衝撃】美女との性行為がヤバすぎるｗｗｗｗ彼女が全く感じないんだがどうすれば感じさせられる？もしかして…"]},{"rank":12,"word":"Xbox","search_keys":["Xbox"],"count":3,"sample_titles":["【悲報】ROG Xbox Ally無印版もひっそりと89,800円→129,800円に4万円値上げ","【速報】Xbox Series　生産終了","メディア「Xboxに必要なのは“新規客”より“かつてのファン”」"]},{"rank":13,"word":"GO","search_keys":["GO"],"count":3,"sample_titles":["【ポケモンGO】孫にポケGO渡したら凄い技マシンめっちゃ使われた","ポケモンGOで8時間20分経過したのにジム攻撃しない奴らなんなの？","ポケモンGO、限定ポケモンのために42キロ歩かせるイベントを開始してプレイヤーが阿鼻叫喚に"]},{"rank":14,"word":"依頼","search_keys":["依頼"],"count":3,"sample_titles":["【悲報】レイヤーさん、5万円で依頼した小道具の出来栄えがひどすぎて発狂","コスプレイヤーさん「5万円で作成依頼した小道具、半年以上待ってるしとんでもないクオリティになってるかも」→実際に渡されたものを見て絶望ｗｗｗｗ","【画像】コスプレイヤーさん、5万円で依頼した小道具の出来栄えがひどすぎて発狂"]},{"rank":15,"word":"発狂","search_keys":["発狂"],"count":3,"sample_titles":["【悲報】レイヤーさん、5万円で依頼した小道具の出来栄えがひどすぎて発狂","【画像】劇場版コナンの脚本家、高市を批判しまくりネトウヨ発狂wwwwwwwwwwwwwwwwwwwwwwwwwww","【画像】コスプレイヤーさん、5万円で依頼した小道具の出来栄えがひどすぎて発狂"]}]},"popular":[]}